Workbook

Sheet Summary
A1: FINANCIAL PLAN SUMMARY - SINGLE PAGE DASHBOARD
A3: Everything on this page is a live link. Change anything on the Inputs sheet and this dashboard, and every other sheet, updates instantly. Built to be reused for any client.
A5: CLIENT & CASH FLOW
A6: Item | B6: Value | C6: Unit | D6: Where It Comes From
A7: Client | B7: =Inputs!B7 -> Client A | D7: Inputs sheet.
A8: Age / Retirement Age / Life Expectancy | B8: =Inputs!B9&" / "&Inputs!B10&" / "&Inputs!B11 -> 24 / 60 / 85 | C8: years | D8: Inputs sheet.
A9: Annual Gross Income | B9: =Inputs!B18 -> 3500000 | C9: ₹ p.a. | D9: Inputs sheet.
A10: Annual Post-Tax Income | B10: =Inputs!B20 -> 2625000 | C10: ₹ p.a. | D10: Gross x (1 - effective tax rate).
A11: Annual Living Expenses | B11: =Inputs!B23 -> 900000 | C11: ₹ p.a. | D11: Monthly expenses x 12.
A12: Annual Insurance Premiums | B12: =Insurance!B78 -> 182300 | C12: ₹ p.a. | D12: Insurance sheet, section H.
A13: Monthly Investible Surplus | B13: =Inputs!B26 -> 128558.33 | C13: ₹ p.m. | D13: Post-tax income less expenses less premiums, divided by 12.
A14: Savings Rate | B14: =Inputs!B27 -> 0.58769524 | C14: % | D14: Investible surplus / post-tax income.
A15: Net Worth Today | B15: =Inputs!B39 -> 1000000 | C15: ₹ | D15: Assets less liabilities.
A17: STEP 1 - PROTECTION (buy this before investing a single rupee)
A18: Item | B18: Value | C18: Unit | D18: Where It Comes From
A19: Term Life Cover to Buy | B19: =Insurance!B48 -> 70000000 | C19: ₹ | D19: Highest of income-multiple, human life value and needs-based methods, less existing cover.
A20: Term Policy Tenure | B20: =Insurance!B49 -> 46 | C20: years | D20: To age 70.
A21: Estimated Term Premium | B21: =Insurance!B51 -> 73500 | C21: ₹ p.a. | D21: Cover / 1 lakh x age-banded rate.
A22: Health Base Cover to Hold | B22: =Insurance!B60 -> 3000000 | C22: ₹ | D22: MAX(age benchmark, 50% of income) x city factor x family loading.
A23: Super Top-Up to Add | B23: =Insurance!B61 -> 9000000 | C23: ₹ | D23: 3x the base cover, deductible equal to the base.
A24: Total Effective Health Cover | B24: =Insurance!B62 -> 12000000 | C24: ₹ | D24: Base + super top-up.
A25: Critical Illness Cover | B25: =Insurance!B71 -> 5000000 | C25: ₹ | D25: MIN(3x gross income, ₹50L).
A26: Personal Accident Cover | B26: =Insurance!B72 -> 20000000 | C26: ₹ | D26: 10x gross income.
A27: TOTAL ANNUAL PREMIUM | B27: =Insurance!B78 -> 182300 | C27: ₹ p.a. | D27: All five policies combined.
A28: Premium as % of Gross Income | B28: =Insurance!B80 -> 0.052085714 | C28: % | D28: Should stay under 5%.
A30: STEP 2 - EMERGENCY FUND & SHORT-TERM GOALS
A31: Item | B31: Value | C31: Unit | D31: Where It Comes From
A32: Emergency Fund Target | B32: =Inputs!B22*Inputs!B64 -> 450000 | C32: ₹ | D32: Monthly expenses x number of months set on the Inputs sheet.
A33: Total Future Cost of All Goals | B33: =Goals!$J$17 -> 71736593 | C33: ₹ | D33: Goals sheet, shortfall column total.
A34: Monthly SIP if All Goals Ran Concurrently | B34: =Goals!$K$17 -> 149116.28 | C34: ₹ p.m. | D34: Goals sheet, monthly SIP column total. The ceiling, not the plan - goals are sequenced.
A36: STEP 3 - RETIREMENT
A37: Item | B37: Value | C37: Unit | D37: Where It Comes From
A38: Years to Retirement | B38: =Inputs!B60 -> 36 | C38: years | D38: Retirement age less current age.
A39: First-Year Retirement Expense (nominal) | B39: =Retirement!B23 -> 5499395.1 | C39: ₹ p.a. | D39: Today's retirement expense inflated to the retirement date.
A40: RETIREMENT CORPUS REQUIRED | B40: =Retirement!B33 -> 1.476611e+08 | C40: ₹ | D40: Present value of inflation-linked withdrawals plus medical buffer and legacy.
A41: Same Corpus in Today's Money | B41: =Retirement!B34 -> 18124037 | C41: ₹ | D41: Corpus deflated back at general inflation.
A42: Value of Existing Corpus at Retirement | B42: =Retirement!B41 -> 31583805 | C42: ₹ | D42: Existing investments compounded at the blended return.
A43: CORPUS GAP TO FUND | B43: =Retirement!B44 -> 1.160773e+08 | C43: ₹ | D43: Required less expected. This is what new investing must create.
A44: Level Monthly SIP (never increased) | B44: =Retirement!B48 -> 22545.181 | C44: ₹ p.m. | D44: Retirement sheet, option 1.
A45: RECOMMENDED: Step-Up SIP, year 1 | B45: =Retirement!B49 -> 8468.2705 | C45: ₹ p.m. | D45: Retirement sheet, option 2. Raise it 10% every year as income grows.
A46: Or One-Time Lumpsum Today | B46: =Retirement!B50 -> 2940172.6 | C46: ₹ | D46: Retirement sheet, option 3.
A47: Wealth Created by Compounding | B47: =Retirement!B54 -> 85680255 | C47: ₹ | D47: Corpus gap less total money actually invested.
A49: STEP 4 - ASSET ALLOCATION OF THE MONTHLY SURPLUS
A50: Item | B50: Value | C50: Unit | D50: Where It Comes From
A51: Equity | B51: =Allocation!B15 -> 96418.75 | C51: ₹ p.m. | D51: Glide-path equity weight at the current age.
A52: Debt (incl. EPF / PPF) | B52: =Allocation!B16 -> 19283.75 | C52: ₹ p.m. | D52: Glide-path debt weight.
A53: Gold | B53: =Allocation!B17 -> 12855.833 | C53: ₹ p.m. | D53: Glide-path gold weight.
A55: FEASIBILITY CHECK
A56: Item | B56: Value | C56: Unit | D56: Where It Comes From
A57: Monthly Investible Surplus | B57: =Inputs!B26 -> 128558.33 | C57: ₹ p.m. | D57: Available to invest.
A58: Committed Now (Critical + High goals + Retirement) | B58: =Goals!B25 -> 114624.52 | C58: ₹ p.m. | D58: Goals sheet affordability block. Only Critical and High priority goals start immediately.
A59: Surplus / (Deficit) | B59: =B57-B58 -> 13933.817 | C59: ₹ p.m. | D59: Negative means the plan as written is not fundable - stretch a horizon, trim a goal amount, or raise income.
A60: Committed as % of Surplus | B60: =IFERROR(B58/B57,0) -> 0.89161483 | C60: % | D60: Under 100% the plan is fundable today.
A61: Deferred Medium / Low priority goal SIPs | B61: =Goals!B23 -> 42960.035 | C61: ₹ p.m. | D61: Started later, funded by instalments released as earlier goals complete and by 8% annual income growth.
A63: ACTION SEQUENCE
A64: 1. Buy the term plan TODAY | D64: Premium is locked for the whole term at age-24 rates. Every year of delay raises the lifetime cost by roughly 8-12%.
A65: 2. Buy a personal health floater independent of the employer | D65: Employer cover vanishes with the job, and pre-existing conditions acquired in the meantime become permanently excluded.
A66: 3. Add the super top-up | D66: Large-claim protection at roughly a quarter of base-policy cost.
A67: 4. Add critical illness and personal accident cover | D67: These replace INCOME during illness or disability, which a hospitalisation policy does not.
A68: 5. Build the emergency fund in liquid funds and sweep-in FDs | D68: 6 months of expenses. Until this exists, every other investment is really a forced-sale risk.
A69: 6. Start the retirement step-up SIP | D69: 36 years of compounding is this client's single largest financial asset.
A70: 7. Layer in goal SIPs by horizon | D70: Under 3 years: debt only. 3-7 years: hybrid. Over 7 years: equity.
A71: 8. Register nominations, write a will, keep a document register | D71: The cheapest and most neglected step in the whole plan.
A72: 9. Review annually and after every life event | D72: Marriage, a child, a job change or a house purchase each invalidate at least one assumption on the Inputs sheet.
A74: DISCLAIMER: this workbook is a planning model, not investment, insurance or tax advice, and I am not a financial adviser. Return and inflation figures are long-run assumptions that no single decade is obliged to deliver. Premium rates are indicative and must be replaced with actual quotes. Tax treatment depends on the regime chosen and on rules that change. Have the plan reviewed by a SEBI-registered investment adviser before acting on it.

Sheet Inputs
A1: 1. CLIENT INPUTS & PLANNING ASSUMPTIONS
A3: HOW TO USE: edit only the YELLOW cells (blue text). Every other cell on every sheet is a live formula that recalculates automatically. Black = formula on this sheet, green = pulled from another sheet.
A5: A. CLIENT PROFILE
A6: Parameter | B6: Value | C6: Unit | D6: Formula / Logic Used
A7: Client Name | B7: Client A | C7: text | D7: Free text label used on the Summary sheet.
A8: Plan Start Date (financial year) | B8: FY 2026-27 | C8: text | D8: Reference year for all 'today's cost' figures.
A9: Current Age | B9: 24 | C9: years | D9: Drives insurance multiples, premium rates and the allocation glide path.
A10: Planned Retirement Age | B10: 60 | C10: years | D10: End of the accumulation phase.
A11: Life Expectancy | B11: 85 | C11: years | D11: Corpus must last until this age. Conservative for a 24-year-old today.
A12: Number of Financial Dependents | B12: 2 | C12: count | D12: Used in the needs-based life cover method.
A13: Family Members to Insure (Health) | B13: 3 | C13: count | D13: Self + spouse + children on a floater policy.
A14: City Tier Factor | B14: 1 | C14: x | D14: Metro = 1.00, Tier-2 = 0.80, Tier-3 = 0.65. Scales the health cover benchmark to local hospitalisation costs.
A16: B. INCOME & CASH FLOW
A17: Parameter | B17: Value | C17: Unit | D17: Formula / Logic Used
A18: Annual Gross Income | B18: 3500000 | C18: ₹ p.a. | D18: Mid-point of the ₹30-40 lakh range. Change to run the plan at either end.
A19: Effective Tax Rate | B19: 0.25 | C19: % | D19: All-in effective rate (new regime, ₹35L salary, incl. cess). Not the marginal slab.
A20: Annual Post-Tax Income | B20: =B18*(1-B19) -> 2625000 | C20: ₹ p.a. | D20: Formula: Gross Income x (1 - Effective Tax Rate)
A21: Monthly Post-Tax Income | B21: =B20/12 -> 218750 | C21: ₹ p.m. | D21: Formula: Annual Post-Tax Income / 12
A22: Monthly Household Expenses | B22: 75000 | C22: ₹ p.m. | D22: All living costs incl. rent, EMIs (interest), lifestyle. Excludes investments.
A23: Annual Household Expenses | B23: =B22*12 -> 900000 | C23: ₹ p.a. | D23: Formula: Monthly Expenses x 12
A24: Annual Insurance Premium Outgo | B24: =Insurance!B78 -> 182300 | C24: ₹ p.a. | D24: Total of term + health + super top-up + critical illness + accident premiums. Pulled from the Insurance sheet.
A25: Annual Investible Surplus | B25: =B20-B23-B24 -> 1542700 | C25: ₹ p.a. | D25: Formula: Post-Tax Income - Living Expenses - Insurance Premiums
A26: Monthly Investible Surplus | B26: =B25/12 -> 128558.33 | C26: ₹ p.m. | D26: Formula: Annual Investible Surplus / 12. This is the budget every SIP on this workbook must fit inside.
A27: Savings Rate | B27: =IF(B20=0,0,B25/B20) -> 0.58769524 | C27: % | D27: Formula: Investible Surplus / Post-Tax Income. Target 40%+ at this age and income.
A28: Expected Annual Income Growth | B28: 0.08 | C28: % | D28: Supports the step-up SIP assumption - if income grows 8%, a 10% SIP step-up is affordable.
A30: C. EXISTING ASSETS & LIABILITIES
A31: Parameter | B31: Value | C31: Unit | D31: Formula / Logic Used
A32: Existing Equity Investments (MF / stocks / NPS-E) | B32: 500000 | C32: ₹ | D32: Market value today.
A33: Existing Debt Investments (EPF / PPF / debt MF) | B33: 300000 | C33: ₹ | D33: Balance today.
A34: Existing Cash, FD & Liquid Funds | B34: 200000 | C34: ₹ | D34: Includes anything already set aside as emergency money.
A35: Total Existing Corpus | B35: =SUM(B32:B34) -> 1000000 | C35: ₹ | D35: Formula: Equity + Debt + Cash
A36: Outstanding Home Loan | B36: 0 | C36: ₹ | D36: Principal outstanding.
A37: Other Loans (car / personal / education) | B37: 0 | C37: ₹ | D37: Principal outstanding.
A38: Total Liabilities | B38: =SUM(B36:B37) -> 0 | C38: ₹ | D38: Formula: Home Loan + Other Loans. Must be fully covered by life insurance.
A39: Net Worth | B39: =B35-B38 -> 1000000 | C39: ₹ | D39: Formula: Total Assets - Total Liabilities
A40: Existing Life Cover (term + employer + others) | B40: 0 | C40: ₹ | D40: Employer group cover is not portable - count it, but do not rely on it.
A41: Existing Health Cover (personal + employer) | B41: 500000 | C41: ₹ | D41: Typically employer floater only, at this stage.
A43: D. INFLATION & RETURN ASSUMPTIONS
A44: Parameter | B44: Value | C44: Unit | D44: Formula / Logic Used
A45: General Inflation (CPI) | B45: 0.06 | C45: % | D45: Long-run Indian CPI assumption. Applied to living expenses and generic goals.
A46: Medical Inflation | B46: 0.1 | C46: % | D46: Runs far above CPI in India. Applied to the health cover requirement.
A47: Education Inflation | B47: 0.08 | C47: % | D47: Applied to child education goals.
A48: Equity Return (long term, pre-retirement) | B48: 0.12 | C48: % | D48: Nominal CAGR assumption for diversified Indian equity over 30+ years.
A49: Debt Return | B49: 0.07 | C49: % | D49: EPF / PPF / debt MF blended nominal return.
A50: Pre-Retirement Equity Allocation | B50: 0.75 | C50: % | D50: Starting equity weight. See the Allocation sheet for the full glide path.
A51: Blended Pre-Retirement Return | B51: =B48*B50+B49*(1-B50) -> 0.1075 | C51: % | D51: Formula: (Equity Return x Equity Weight) + (Debt Return x Debt Weight). The single growth rate used for all accumulation maths.
A52: Post-Retirement Portfolio Return | B52: 0.075 | C52: % | D52: Lower-risk drawdown portfolio (roughly 30% equity / 70% debt).
A53: Annual SIP Step-Up Rate | B53: 0.1 | C53: % | D53: How much the SIP is increased each year. Should be <= expected income growth.
A54: Real Return - Pre-Retirement | B54: =(1+B51)/(1+B45)-1 -> 0.044811321 | C54: % | D54: Formula: (1 + Nominal Return) / (1 + Inflation) - 1. Fisher equation. Purchasing-power growth, not the crude 'return minus inflation'.
A55: Real Return - Post-Retirement | B55: =(1+B52)/(1+B45)-1 -> 0.014150943 | C55: % | D55: Formula: (1 + Post-Ret Return) / (1 + Inflation) - 1. Used to size the retirement corpus so withdrawals can rise with inflation every year.
A56: Real Discount Rate for Insurance (conservative) | B56: =(1+B49)/(1+B45)-1 -> 0.0094339623 | C56: % | D56: Formula: (1 + Debt Return) / (1 + Inflation) - 1. Life cover is discounted at a SAFE rate, not an equity rate - the family should not have to take market risk.
A58: E. DERIVED PLANNING PARAMETERS
A59: Parameter | B59: Value | C59: Unit | D59: Formula / Logic Used
A60: Years to Retirement | B60: =B10-B9 -> 36 | C60: years | D60: Formula: Retirement Age - Current Age
A61: Months to Retirement | B61: =B60*12 -> 432 | C61: months | D61: Formula: Years to Retirement x 12
A62: Years in Retirement | B62: =B11-B10 -> 25 | C62: years | D62: Formula: Life Expectancy - Retirement Age. The corpus must fund this many years.
A63: Retirement Expense as % of Current Expense | B63: 0.75 | C63: % | D63: Work-related and child-related costs fall away; healthcare rises. 70-80% is the standard planning band.
A64: Emergency Fund Target (months of expenses) | B64: 6 | C64: months | D64: 6 months for a salaried single earner; 9-12 if income is variable or single-income with dependents.
A66: ASSUMPTION LOG: income ₹35L is the mid-point of the ₹30-40L range stated by the client. Tax rate, expenses, existing assets and cover are placeholders - overwrite with actuals per client. Return and inflation figures are long-run planning assumptions, not guarantees; equity returns are not linear and any single decade can undershoot.

Sheet Insurance
A1: 2. INSURANCE PLANNING - LIFE, HEALTH, CRITICAL ILLNESS, ACCIDENT
A3: PRIORITY ORDER: risk cover is bought BEFORE any investment. An uninsured medical event or death destroys a portfolio far faster than any market fall. Buy term + health first, then invest the balance.
A5: A. CLIENT SNAPSHOT (pulled from the Inputs sheet)
A6: Parameter | B6: Value | C6: Unit | D6: Formula / Logic Used
A7: Current Age | B7: =Inputs!B9 -> 24 | C7: years | D7: Link to Inputs.
A8: Annual Gross Income | B8: =Inputs!B18 -> 3500000 | C8: ₹ p.a. | D8: Link to Inputs.
A9: Annual Post-Tax Income | B9: =Inputs!B20 -> 2625000 | C9: ₹ p.a. | D9: Link to Inputs.
A10: Years to Retirement | B10: =Inputs!B60 -> 36 | C10: years | D10: Income-earning years remaining.
A11: Total Liabilities | B11: =Inputs!B38 -> 0 | C11: ₹ | D11: Must be extinguished by the death benefit.
A12: Total Existing Corpus | B12: =Inputs!B35 -> 1000000 | C12: ₹ | D12: Assets the family already has - reduces cover needed.
A13: Existing Life Cover | B13: =Inputs!B40 -> 0 | C13: ₹ | D13: Deducted from the requirement.
A14: Existing Health Cover | B14: =Inputs!B41 -> 500000 | C14: ₹ | D14: Deducted from the requirement.
A15: Safe Real Discount Rate | B15: =Inputs!B56 -> 0.0094339623 | C15: % | D15: Debt-return-based real rate. Used for all present-value insurance maths.
A17: B. LIFE INSURANCE - METHOD 1: INCOME MULTIPLE (THUMB RULE)
A18: Parameter | B18: Value | C18: Unit | D18: Formula / Logic Used
A19: Applicable Income Multiple | B19: =INDEX(Tables!$B$5:$B$10,MATCH(B7,Tables!$A$5:$A$10,1)) -> 20 | C19: x | D19: Formula: INDEX(multiples, MATCH(Age, age-bands, 1)). Approximate-match lookup on the Tables sheet: the multiple falls as the client ages because fewer earning years remain.
A20: Cover by Income Multiple | B20: =B8*B19 -> 70000000 | C20: ₹ | D20: Formula: Annual Gross Income x Multiple. Fast sanity check only - it ignores liabilities, assets and actual family need.
A22: C. LIFE INSURANCE - METHOD 2: HUMAN LIFE VALUE (INCOME REPLACEMENT)
A23: Parameter | B23: Value | C23: Unit | D23: Formula / Logic Used
A24: Self-Consumption Share of Income | B24: 0.3 | C24: % | D24: The portion the earner spends on themselves, which the family no longer needs. 25-35% is standard.
A25: Income Available to Family (annual) | B25: =B9*(1-B24) -> 1837500 | C25: ₹ p.a. | D25: Formula: Post-Tax Income x (1 - Self-Consumption Share)
A26: Present Value of Lost Future Income | B26: =PV(B15,B10,-B25) -> 55866646 | C26: ₹ | D26: Formula: PV(real safe rate, years to retirement, -annual income to family). Using the REAL rate means the payout can be raised with inflation every year, so the family's standard of living is preserved.
A27: Add: Outstanding Liabilities | B27: =B11 -> 0 | C27: ₹ | D27: Loans must be cleared, not serviced, on death.
A28: Less: Existing Corpus | B28: =-B12 -> -1000000 | C28: ₹ | D28: Assets already available to the family.
A29: Human Life Value Cover Required | B29: =MAX(0,SUM(B26:B28)) -> 54866646 | C29: ₹ | D29: Formula: PV of income + Liabilities - Existing Corpus
A31: D. LIFE INSURANCE - METHOD 3: NEEDS-BASED (MOST ACCURATE)
A32: Parameter | B32: Value | C32: Unit | D32: Formula / Logic Used
A33: Family Expenses if Earner Dies (annual) | B33: =Inputs!B23*0.75 -> 675000 | C33: ₹ p.a. | D33: Formula: Current Annual Household Expenses x 75%. Household costs fall, but not proportionally - one fewer person does not mean 33% less spending.
A34: Dependency Period | B34: =Inputs!B11-Inputs!B9 -> 61 | C34: years | D34: Formula: Life Expectancy - Current Age. The family needs income support for the SPOUSE'S whole remaining life, not just until the earner would have retired.
A35: Present Value of Family Expenses | B35: =PV(B15,B34,-B33) -> 31198751 | C35: ₹ | D35: Formula: PV(real safe rate, dependency years, -annual family expenses)
A36: Add: Outstanding Liabilities | B36: =B11 -> 0 | C36: ₹ | D36: Home loan / other loans repaid in full.
A37: Add: Children's Education Corpus (today's value) | B37: 3000000 | C37: ₹ | D37: Present-day cost of the education goals the earner promised to fund.
A38: Add: Children's Marriage Corpus (today's value) | B38: 2500000 | C38: ₹ | D38: Present-day cost. Set to 0 if not a planned goal.
A39: Add: Funeral / Immediate Estate Costs | B39: 500000 | C39: ₹ | D39: Immediate liquidity for the family in the first 6 months.
A40: Less: Existing Corpus | B40: =-B12 -> -1000000 | C40: ₹ | D40: Assets the family can draw on.
A41: Needs-Based Cover Required | B41: =MAX(0,SUM(B35:B40)) -> 36198751 | C41: ₹ | D41: Formula: PV of expenses + Liabilities + Education + Marriage + Estate costs - Existing Corpus
A43: E. LIFE INSURANCE - RECOMMENDATION
A44: Parameter | B44: Value | C44: Unit | D44: Formula / Logic Used
A45: Highest of the Three Methods | B45: =MAX(B20,B29,B41) -> 70000000 | C45: ₹ | D45: Formula: MAX(Income Multiple, HLV, Needs-Based). Always plan to the highest - under-insurance cannot be fixed after the event.
A46: Less: Existing Life Cover | B46: =-B13 -> 0 | C46: ₹ | D46: Employer group cover counts here but disappears when the job does.
A47: Additional Cover Needed | B47: =MAX(0,B45+B46) -> 70000000 | C47: ₹ | D47: Formula: Highest Requirement - Existing Cover, floored at zero.
A48: RECOMMENDED TERM COVER (rounded up to ₹25L) | B48: =CEILING(B47,2500000) -> 70000000 | C48: ₹ | D48: Formula: CEILING(Additional Cover, 2500000). Insurers sell in round slabs; rounding up is free protection.
A49: Recommended Policy Term (to age 70) | B49: =70-B7 -> 46 | C49: years | D49: Formula: 70 - Current Age. Cover must run past retirement age because liabilities and dependants can outlive the salary. Buying at 24 locks this premium for the whole term.
A50: Premium Rate per ₹1 Lakh of Cover | B50: =INDEX(Tables!$E$5:$E$11,MATCH(B7,Tables!$D$5:$D$11,1)) -> 105 | C50: ₹ p.a. | D50: Formula: INDEX(rates, MATCH(Age, age-bands, 1)). Age-banded lookup from the Tables sheet - this is why buying at 24 rather than 34 roughly halves the lifetime cost.
A51: Estimated Annual Term Premium | B51: =B48/100000*B50 -> 73500 | C51: ₹ p.a. | D51: Formula: (Cover / 100,000) x Rate per Lakh
A52: Term Premium as % of Gross Income | B52: =IFERROR(B51/B8,0) -> 0.021 | C52: % | D52: Formula: Premium / Gross Income. Total protection cost should stay under ~5% of income.
A54: F. HEALTH INSURANCE
A55: Parameter | B55: Value | C55: Unit | D55: Formula / Logic Used
A56: Age-Based Cover Benchmark | B56: =INDEX(Tables!$H$5:$H$9,MATCH(B7,Tables!$G$5:$G$9,1)) -> 500000 | C56: ₹ | D56: Formula: INDEX(benchmarks, MATCH(Age, age-bands, 1)). Minimum sensible base cover for the age band.
A57: Income-Linked Minimum (50% of gross) | B57: =B8*0.5 -> 1750000 | C57: ₹ | D57: Formula: Gross Income x 50%. A high earner has a higher standard of care and higher out-of-pocket exposure than the age benchmark alone implies.
A58: City Tier Factor | B58: =Inputs!B14 -> 1 | C58: x | D58: Metro hospitalisation costs 25-50% more than Tier-3.
A59: Family Size Loading | B59: =1+(Inputs!B13-1)*0.25 -> 1.5 | C59: x | D59: Formula: 1 + (Family Members - 1) x 25%. A floater covering 3 people needs more than a single-life sum insured, but not 3x - claims rarely coincide.
A60: RECOMMENDED BASE COVER (floater) | B60: =CEILING(MAX(B56,B57)*B58*B59,500000) -> 3000000 | C60: ₹ | D60: Formula: CEILING( MAX(age benchmark, income minimum) x City Factor x Family Loading, 500000 )
A61: RECOMMENDED SUPER TOP-UP | B61: =CEILING(B60*3,500000) -> 9000000 | C61: ₹ | D61: Formula: Base Cover x 3, rounded to ₹5L. A super top-up with a deductible equal to the base cover buys large protection for roughly a quarter of the price. This is the single most cost-efficient move in health planning.
A62: Total Effective Health Cover | B62: =B60+B61 -> 12000000 | C62: ₹ | D62: Formula: Base + Super Top-Up
A63: Less: Existing Health Cover | B63: =-B14 -> -500000 | C63: ₹ | D63: Employer cover ends with employment - treat it as a bonus, not the plan.
A64: Additional Base Cover to Buy | B64: =MAX(0,B60+B63) -> 2500000 | C64: ₹ | D64: Formula: Recommended Base - Existing Cover
A65: Health Premium Rate per ₹1 Lakh | B65: =INDEX(Tables!$K$5:$K$9,MATCH(B7,Tables!$J$5:$J$9,1)) -> 1400 | C65: ₹ p.a. | D65: Formula: INDEX(rates, MATCH(Age, age-bands, 1))
A66: Estimated Base Policy Premium | B66: =B60/100000*B65 -> 42000 | C66: ₹ p.a. | D66: Formula: (Base Cover / 100,000) x Rate per Lakh
A67: Estimated Super Top-Up Premium | B67: =B61/100000*B65*Tables!$B$25 -> 37800 | C67: ₹ p.a. | D67: Formula: (Top-Up Cover / 100,000) x Rate per Lakh x Top-Up Discount Factor
A69: G. CRITICAL ILLNESS & PERSONAL ACCIDENT
A70: Parameter | B70: Value | C70: Unit | D70: Formula / Logic Used
A71: Critical Illness Cover Recommended | B71: =CEILING(MIN(B8*3,5000000),500000) -> 5000000 | C71: ₹ | D71: Formula: MIN(3 x Gross Income, ₹50L), rounded to ₹5L. A lump sum on diagnosis - it replaces INCOME during treatment and recovery, which a hospitalisation policy does not do.
A72: Personal Accident Cover Recommended | B72: =CEILING(MIN(B8*10,20000000),500000) -> 20000000 | C72: ₹ | D72: Formula: MIN(10 x Gross Income, ₹2 Cr), rounded to ₹5L. Insurers rarely underwrite personal accident above ~₹2 Cr. Covers permanent/partial disability, the risk that is statistically likelier than death at age 24 and financially worse.
A73: Estimated Critical Illness Premium | B73: =B71/100000*Tables!$B$26 -> 11000 | C73: ₹ p.a. | D73: Formula: (CI Cover / 100,000) x CI Rate per Lakh
A74: Estimated Personal Accident Premium | B74: =B72/100000*Tables!$B$27 -> 18000 | C74: ₹ p.a. | D74: Formula: (PA Cover / 100,000) x PA Rate per Lakh
A76: H. TOTAL PROTECTION COST
A77: Parameter | B77: Value | C77: Unit | D77: Formula / Logic Used
A78: TOTAL ANNUAL PREMIUM OUTGO | B78: =B51+B66+B67+B73+B74 -> 182300 | C78: ₹ p.a. | D78: Formula: Term + Health Base + Super Top-Up + Critical Illness + Personal Accident. This figure feeds back into the Inputs sheet and is deducted before any SIP is sized.
A79: Monthly Equivalent | B79: =B78/12 -> 15191.667 | C79: ₹ p.m. | D79: Formula: Total Annual Premium / 12
A80: Total Premium as % of Gross Income | B80: =IFERROR(B78/B8,0) -> 0.052085714 | C80: % | D80: Formula: Total Premium / Gross Income. Green under 5%, review above 7%.
A81: Section 80D Deduction Available (old regime) | B81: =MIN(B66+B67,25000) -> 25000 | C81: ₹ | D81: Formula: MIN(health premiums, ₹25,000) for self+family under 60. Only claimable under the OLD tax regime; ₹0 benefit under the new regime.
A83: I. FUTURE HEALTH COVER REQUIREMENT (medical inflation)
A84: Years From Now | B84: Age Then | C84: Cover Needed Then (₹) | D84: Formula / Logic Used
A85: 0 | B85: =B7+A85 -> 24 | C85: =FV(Inputs!B46,A85,0,-$B$62) -> 12000000 | D85: Formula: FV(Medical Inflation, Years, 0, -Today's Total Cover). Today's cover buys progressively less treatment; review and step up the sum insured every 5 years.
A86: 5 | B86: =B7+A86 -> 29 | C86: =FV(Inputs!B46,A86,0,-$B$62) -> 19326120 | D86: Formula: FV(Medical Inflation, Years, 0, -Today's Total Cover). Today's cover buys progressively less treatment; review and step up the sum insured every 5 years.
A87: 10 | B87: =B7+A87 -> 34 | C87: =FV(Inputs!B46,A87,0,-$B$62) -> 31124910 | D87: Formula: FV(Medical Inflation, Years, 0, -Today's Total Cover). Today's cover buys progressively less treatment; review and step up the sum insured every 5 years.
A88: 15 | B88: =B7+A88 -> 39 | C88: =FV(Inputs!B46,A88,0,-$B$62) -> 50126978 | D88: Formula: FV(Medical Inflation, Years, 0, -Today's Total Cover). Today's cover buys progressively less treatment; review and step up the sum insured every 5 years.
A89: 20 | B89: =B7+A89 -> 44 | C89: =FV(Inputs!B46,A89,0,-$B$62) -> 80729999 | D89: Formula: FV(Medical Inflation, Years, 0, -Today's Total Cover). Today's cover buys progressively less treatment; review and step up the sum insured every 5 years.
A90: 25 | B90: =B7+A90 -> 49 | C90: =FV(Inputs!B46,A90,0,-$B$62) -> 1.3001647e+08 | D90: Formula: FV(Medical Inflation, Years, 0, -Today's Total Cover). Today's cover buys progressively less treatment; review and step up the sum insured every 5 years.
A91: 30 | B91: =B7+A91 -> 54 | C91: =FV(Inputs!B46,A91,0,-$B$62) -> 2.0939283e+08 | D91: Formula: FV(Medical Inflation, Years, 0, -Today's Total Cover). Today's cover buys progressively less treatment; review and step up the sum insured every 5 years.
A92: 36 | B92: =B7+A92 -> 60 | C92: =FV(Inputs!B46,A92,0,-$B$62) -> 3.7095217e+08 | D92: Formula: FV(Medical Inflation, Years, 0, -Today's Total Cover). Today's cover buys progressively less treatment; review and step up the sum insured every 5 years.
A94: ACTION ORDER: (1) buy the term plan today - premium is locked for life at age 24 and rises ~8-12% per year of delay; (2) buy a personal health floater independent of the employer; (3) add the super top-up; (4) add critical illness and personal accident; (5) only then start investing the surplus. Premiums shown are indicative retail estimates - replace with actual quotes. Nominate correctly and disclose everything material; a rejected claim is worse than no cover.

Sheet Goals
A1: 3. GOAL PLANNING - EMERGENCY FUND, SHORT TERM & LONG TERM
A2: Edit the YELLOW cells only (goal name, horizon, today's cost, inflation rate, money already earmarked, expected return). Every other column is a live formula. Add rows inside the table and copy the formulas down.
A4: Goal | B4: Priority | C4: Years to Goal | D4: Cost Today (₹) | E4: Inflation Rate | F4: Future Cost at Goal Date (₹) | G4: Already Earmarked (₹) | H4: Expected Return | I4: FV of Earmarked (₹) | J4: Shortfall to Fund (₹) | K4: Monthly SIP Needed (₹) | L4: One-Time Lumpsum Today (₹)
A5: Emergency Fund (6 months expenses) | B5: Critical | C5: 1 | D5: =Inputs!B22*Inputs!B64 -> 450000 | E5: =Inputs!$B$45 -> 0.06 | F5: =IF($C5="","",FV($E5,$C5,0,-$D5)) -> 477000 | G5: =Inputs!B34 -> 200000 | H5: 0.065 | I5: =IF($C5="","",FV($H5,$C5,0,-$G5)) -> 213000 | J5: =IF($C5="","",MAX(0,$F5-$I5)) -> 264000 | K5: =IF($C5="","",IF($J5=0,0,-PMT($H5/12,$C5*12,0,$J5))) -> 21352.254 | L5: =IF($C5="","",$J5/(1+$H5)^$C5) -> 247887.32
A6: International Holiday | B6: Low | C6: 2 | D6: 300000 | E6: =Inputs!$B$45 -> 0.06 | F6: =IF($C6="","",FV($E6,$C6,0,-$D6)) -> 337080 | G6: 0 | H6: 0.08 | I6: =IF($C6="","",FV($H6,$C6,0,-$G6)) -> 0 | J6: =IF($C6="","",MAX(0,$F6-$I6)) -> 337080 | K6: =IF($C6="","",IF($J6=0,0,-PMT($H6/12,$C6*12,0,$J6))) -> 12998.015 | L6: =IF($C6="","",$J6/(1+$H6)^$C6) -> 288991.77
A7: Upskilling / Certification / PG | B7: High | C7: 5 | D7: 1000000 | E7: =Inputs!$B$47 -> 0.08 | F7: =IF($C7="","",FV($E7,$C7,0,-$D7)) -> 1469328.1 | G7: 0 | H7: 0.1 | I7: =IF($C7="","",FV($H7,$C7,0,-$G7)) -> 0 | J7: =IF($C7="","",MAX(0,$F7-$I7)) -> 1469328.1 | K7: =IF($C7="","",IF($J7=0,0,-PMT($H7/12,$C7*12,0,$J7))) -> 18974.479 | L7: =IF($C7="","",$J7/(1+$H7)^$C7) -> 912337.13
A8: Wedding | B8: High | C8: 5 | D8: 1500000 | E8: =Inputs!$B$45 -> 0.06 | F8: =IF($C8="","",FV($E8,$C8,0,-$D8)) -> 2007338.4 | G8: 0 | H8: 0.1 | I8: =IF($C8="","",FV($H8,$C8,0,-$G8)) -> 0 | J8: =IF($C8="","",MAX(0,$F8-$I8)) -> 2007338.4 | K8: =IF($C8="","",IF($J8=0,0,-PMT($H8/12,$C8*12,0,$J8))) -> 25922.188 | L8: =IF($C8="","",$J8/(1+$H8)^$C8) -> 1246399.2
A9: Car Purchase (down payment + on-road) | B9: Medium | C9: 7 | D9: 1000000 | E9: =Inputs!$B$45 -> 0.06 | F9: =IF($C9="","",FV($E9,$C9,0,-$D9)) -> 1503630.3 | G9: 0 | H9: 0.11 | I9: =IF($C9="","",FV($H9,$C9,0,-$G9)) -> 0 | J9: =IF($C9="","",MAX(0,$F9-$I9)) -> 1503630.3 | K9: =IF($C9="","",IF($J9=0,0,-PMT($H9/12,$C9*12,0,$J9))) -> 11962.536 | L9: =IF($C9="","",$J9/(1+$H9)^$C9) -> 724236.16
A10: Home Down Payment (20% of ₹1.5 Cr) | B10: High | C10: 10 | D10: 3000000 | E10: 0.07 | F10: =IF($C10="","",FV($E10,$C10,0,-$D10)) -> 5901454.1 | G10: 0 | H10: 0.11 | I10: =IF($C10="","",FV($H10,$C10,0,-$G10)) -> 0 | J10: =IF($C10="","",MAX(0,$F10-$I10)) -> 5901454.1 | K10: =IF($C10="","",IF($J10=0,0,-PMT($H10/12,$C10*12,0,$J10))) -> 27195.874 | L10: =IF($C10="","",$J10/(1+$H10)^$C10) -> 2078400.5
A11: Child - Higher Education (undergrad) | B11: High | C11: 22 | D11: 3000000 | E11: =Inputs!$B$47 -> 0.08 | F11: =IF($C11="","",FV($E11,$C11,0,-$D11)) -> 16309621 | G11: 0 | H11: 0.12 | I11: =IF($C11="","",FV($H11,$C11,0,-$G11)) -> 0 | J11: =IF($C11="","",MAX(0,$F11-$I11)) -> 16309621 | K11: =IF($C11="","",IF($J11=0,0,-PMT($H11/12,$C11*12,0,$J11))) -> 12711.451 | L11: =IF($C11="","",$J11/(1+$H11)^$C11) -> 1347868
A12: Child - Post Graduation / Abroad | B12: Medium | C12: 26 | D12: 4000000 | E12: =Inputs!$B$47 -> 0.08 | F12: =IF($C12="","",FV($E12,$C12,0,-$D12)) -> 29585413 | G12: 0 | H12: 0.12 | I12: =IF($C12="","",FV($H12,$C12,0,-$G12)) -> 0 | J12: =IF($C12="","",MAX(0,$F12-$I12)) -> 29585413 | K12: =IF($C12="","",IF($J12=0,0,-PMT($H12/12,$C12*12,0,$J12))) -> 13891.079 | L12: =IF($C12="","",$J12/(1+$H12)^$C12) -> 1553849.8
A13: Child - Marriage | B13: Medium | C13: 30 | D13: 2500000 | E13: =Inputs!$B$45 -> 0.06 | F13: =IF($C13="","",FV($E13,$C13,0,-$D13)) -> 14358728 | G13: 0 | H13: 0.12 | I13: =IF($C13="","",FV($H13,$C13,0,-$G13)) -> 0 | J13: =IF($C13="","",MAX(0,$F13-$I13)) -> 14358728 | K13: =IF($C13="","",IF($J13=0,0,-PMT($H13/12,$C13*12,0,$J13))) -> 4108.4049 | L13: =IF($C13="","",$J13/(1+$H13)^$C13) -> 479264.53
F14: =IF($C14="","",FV($E14,$C14,0,-$D14)) | I14: =IF($C14="","",FV($H14,$C14,0,-$G14)) | J14: =IF($C14="","",MAX(0,$F14-$I14)) | K14: =IF($C14="","",IF($J14=0,0,-PMT($H14/12,$C14*12,0,$J14))) | L14: =IF($C14="","",$J14/(1+$H14)^$C14)
F15: =IF($C15="","",FV($E15,$C15,0,-$D15)) | I15: =IF($C15="","",FV($H15,$C15,0,-$G15)) | J15: =IF($C15="","",MAX(0,$F15-$I15)) | K15: =IF($C15="","",IF($J15=0,0,-PMT($H15/12,$C15*12,0,$J15))) | L15: =IF($C15="","",$J15/(1+$H15)^$C15)
F16: =IF($C16="","",FV($E16,$C16,0,-$D16)) | I16: =IF($C16="","",FV($H16,$C16,0,-$G16)) | J16: =IF($C16="","",MAX(0,$F16-$I16)) | K16: =IF($C16="","",IF($J16=0,0,-PMT($H16/12,$C16*12,0,$J16))) | L16: =IF($C16="","",$J16/(1+$H16)^$C16)
A17: TOTAL | D17: =SUM(D5:D16) -> 16750000 | F17: =SUM(F5:F16) -> 71949593 | G17: =SUM(G5:G16) -> 200000 | I17: =SUM(I5:I16) -> 213000 | J17: =SUM(J5:J16) -> 71736593 | K17: =SUM(K5:K16) -> 149116.28 | L17: =SUM(L5:L16) -> 8879234.5
A19: AFFORDABILITY CHECK - WHAT IS ACTUALLY FUNDABLE TODAY
A20: Monthly Investible Surplus available | B20: =Inputs!B26 -> 128558.33 | D20: From the Inputs sheet: post-tax income less living expenses less insurance premiums.
A21: Monthly SIP if ALL goals ran concurrently | B21: =K17 -> 149116.28 | D21: Formula: SUM of the Monthly SIP Needed column. Goals rarely all start on day one, so treat this as the ceiling, not the plan.
A22: Monthly SIP for CRITICAL + HIGH priority goals | B22: =SUMIF($B$5:$B$16,"Critical",$K$5:$K$16)+SUMIF($B$5:$B$16,"High",$K$5:$K$16) -> 106156.25 | D22: Formula: SUMIF(priority range, "Critical", SIP range) + SUMIF(priority range, "High", SIP range). Adds only the SIPs whose priority cell reads Critical or High. This is what starts now.
A23: Monthly SIP for MEDIUM + LOW priority goals (deferrable) | B23: =B21-B22 -> 42960.035 | D23: Formula: All-goals SIP - Critical & High SIP. Start these as income rises or as earlier goals complete and free up their instalment.
A24: Monthly SIP for Retirement (step-up, year 1) | B24: =Retirement!B49 -> 8468.2705 | D24: Pulled from the Retirement sheet. Non-negotiable - it has the longest runway and the least ability to be made up later.
A25: COMMITTED NOW (Critical + High goals + Retirement) | B25: =B22+B24 -> 114624.52 | D25: Formula: Critical & High goal SIPs + Retirement SIP. The monthly commitment the client actually takes on today.
A26: Surplus / (Deficit) after what is committed now | B26: =B20-B25 -> 13933.817 | D26: Formula: Investible Surplus - Committed Now. Positive means the plan is fundable as written. Negative means stretch a horizon, trim a goal amount, or raise income before adding anything.
A27: Committed as % of Investible Surplus | B27: =IFERROR(B25/B20,0) -> 0.89161483 | D27: Formula: Committed Now / Investible Surplus. Anything under 100% is fundable.
A28: Surplus / (Deficit) if every goal ran concurrently | B28: =B20-B21-B24 -> -29026.219 | D28: Formula: Surplus - All-goals SIP - Retirement SIP. Usually negative, and that is the point: it is the arithmetic proof that goals must be SEQUENCED, not stacked.
A30: SEQUENCING NOTE: the emergency fund is a one-year push - once it is full, its entire instalment is released to the next goal. Every completed goal does the same. That rolling release, plus the 8% expected income growth on the Inputs sheet, is how the medium and low priority goals get funded without ever exceeding the surplus.
A33: COLUMN FORMULAS EXPLAINED
A34: Future Cost at Goal Date | B34: Formula: FV(Inflation, Years, 0, -Cost Today) | E34: Compounds today's price forward at the goal's own inflation rate. Education inflates faster than groceries, so each goal carries its own rate.
A35: FV of Earmarked | B35: Formula: FV(Expected Return, Years, 0, -Already Earmarked) | E35: Money already set aside for this goal keeps growing. Only the shortfall needs new money.
A36: Shortfall to Fund | B36: Formula: MAX(0, Future Cost - FV of Earmarked) | E36: The real funding requirement, floored at zero so an over-funded goal does not net off against others.
A37: Monthly SIP Needed | B37: Formula: -PMT(Return/12, Years*12, 0, Shortfall) | E37: The level monthly instalment whose future value equals the shortfall. Negated because PMT returns a cash OUTFLOW as a negative number.
A38: One-Time Lumpsum Today | B38: Formula: Shortfall / (1 + Return)^Years | E38: The single amount invested today that grows into the shortfall. Present value of a single future sum.
A39: Expected Return set by horizon | B39: under 3 yrs 6.5-8% (liquid/arbitrage) | 3-7 yrs 9-11% (hybrid) | over 7 yrs 12% (equity) | E39: Never fund a goal under 3 years away with equity. The horizon dictates the asset class, and the asset class dictates the return you may assume.

Sheet Retirement
A1: 4. RETIREMENT PLANNING - CORPUS REQUIRED & HOW TO GET THERE
A3: The corpus is sized so that withdrawals RISE WITH INFLATION every single year of retirement and the money still lasts to life expectancy. That is what the real-rate annuity-due present value below does.
A5: A. RETIREMENT PARAMETERS
A6: Parameter | B6: Value | C6: Unit | D6: Formula / Logic Used
A7: Current Age | B7: =Inputs!B9 -> 24 | C7: years | D7: Link to Inputs.
A8: Retirement Age | B8: =Inputs!B10 -> 60 | C8: years | D8: Link to Inputs.
A9: Life Expectancy | B9: =Inputs!B11 -> 85 | C9: years | D9: Link to Inputs.
A10: Years to Retirement (accumulation) | B10: =Inputs!B60 -> 36 | C10: years | D10: Formula: Retirement Age - Current Age. 36 years of compounding is the single biggest asset this client has.
A11: Years in Retirement (drawdown) | B11: =Inputs!B62 -> 25 | C11: years | D11: Formula: Life Expectancy - Retirement Age
A12: General Inflation | B12: =Inputs!B45 -> 0.06 | C12: % | D12: Link to Inputs.
A13: Blended Pre-Retirement Return | B13: =Inputs!B51 -> 0.1075 | C13: % | D13: Link to Inputs.
A14: Post-Retirement Return | B14: =Inputs!B52 -> 0.075 | C14: % | D14: Link to Inputs.
A15: Real Post-Retirement Return | B15: =Inputs!B55 -> 0.014150943 | C15: % | D15: Formula: (1+Post-Ret Return)/(1+Inflation)-1. The rate at which the corpus outgrows inflation during drawdown.
A16: Annual SIP Step-Up Rate | B16: =Inputs!B53 -> 0.1 | C16: % | D16: Link to Inputs.
A18: B. RETIREMENT EXPENSE PROJECTION
A19: Parameter | B19: Value | C19: Unit | D19: Formula / Logic Used
A20: Current Annual Household Expenses | B20: =Inputs!B23 -> 900000 | C20: ₹ p.a. | D20: Link to Inputs.
A21: Retirement Expense Ratio | B21: =Inputs!B63 -> 0.75 | C21: % | D21: Link to Inputs. Commuting, work clothes, child costs and EMIs go; healthcare and leisure rise.
A22: Retirement Expenses in TODAY'S money | B22: =B20*B21 -> 675000 | C22: ₹ p.a. | D22: Formula: Current Annual Expenses x Retirement Expense Ratio
A23: Annual Expenses in the FIRST year of retirement | B23: =FV(B12,B10,0,-B22) -> 5499395.1 | C23: ₹ p.a. | D23: Formula: FV(Inflation, Years to Retirement, 0, -Today's Retirement Expense). This is the number that shocks clients: 36 years of 6% inflation multiplies today's cost roughly 8x.
A24: Monthly Expenses in the first year of retirement | B24: =B23/12 -> 458282.92 | C24: ₹ p.m. | D24: Formula: Annual first-year retirement expense / 12
A26: C. CORPUS REQUIRED AT RETIREMENT
A27: Parameter | B27: Value | C27: Unit | D27: Formula / Logic Used
A28: Corpus to Fund Inflation-Linked Living Expenses | B28: =PV(B15,B11,-B23,0,1) -> 1.1674842e+08 | C28: ₹ | D28: Formula: PV(Real Post-Ret Return, Years in Retirement, -First-Year Expense, 0, 1). Annuity-DUE (the trailing 1) because the year's expenses are withdrawn at the START of the year. Discounting at the REAL rate is what lets every future withdrawal rise with inflation.
A29: Medical Buffer (today's value) | B29: 1000000 | C29: ₹ | D29: A ring-fenced sum for treatment not covered by insurance. Grows at MEDICAL inflation, not CPI.
A30: Medical Buffer at Retirement | B30: =FV(Inputs!B46,B10,0,-B29) -> 30912681 | C30: ₹ | D30: Formula: FV(Medical Inflation, Years to Retirement, 0, -Medical Buffer Today)
A31: Legacy / Estate to Leave Behind (today's value) | B31: 0 | C31: ₹ | D31: Set above zero if the client wants to bequeath a specific amount.
A32: Legacy at Retirement | B32: =FV(B12,B10,0,-B31) -> 0 | C32: ₹ | D32: Formula: FV(Inflation, Years to Retirement, 0, -Legacy Today)
A33: TOTAL RETIREMENT CORPUS REQUIRED | B33: =B28+B30+B32 -> 1.476611e+08 | C33: ₹ | D33: Formula: Living Expense Corpus + Medical Buffer + Legacy
A34: Corpus in TODAY'S purchasing power | B34: =B33/(1+B12)^B10 -> 18124037 | C34: ₹ | D34: Formula: Corpus / (1 + Inflation) ^ Years to Retirement. Deflating the headline number back to today makes it comprehensible - the crore figure is large mostly because money shrinks.
A35: Cross-check: 30x First-Year Expense | B35: =B23*30 -> 1.6498185e+08 | C35: ₹ | D35: Formula: First-Year Retirement Expense x 30. The 3.33% safe-withdrawal thumb rule. Should land within ~15% of the PV answer; a big divergence means an assumption needs revisiting.
A36: Implied Initial Withdrawal Rate | B36: =IFERROR(B23/B33,0) -> 0.037243357 | C36: % | D36: Formula: First-Year Expense / Total Corpus. Anything at or under 4% is historically survivable over a 25-year retirement; under 3.5% for a 25-year-plus retirement.
A38: D. WHAT THE CLIENT ALREADY HAS
A39: Parameter | B39: Value | C39: Unit | D39: Formula / Logic Used
A40: Existing Corpus Available for Retirement | B40: =Inputs!B32+Inputs!B33 -> 800000 | C40: ₹ | D40: Formula: Existing Equity + Existing Debt. Deliberately EXCLUDES the cash and FD balance, because that money is earmarked as the emergency fund on the Goals sheet and counting it twice would overstate the retirement position.
A41: Future Value of Existing Corpus at Retirement | B41: =FV(B13,B10,0,-B40) -> 31583805 | C41: ₹ | D41: Formula: FV(Blended Return, Years to Retirement, 0, -Existing Corpus). Money already invested does the heavy lifting - it compounds for the full 36 years untouched.
A42: Expected EPF Accumulation at Retirement | B42: 0 | C42: ₹ | D42: Optional. Enter the projected EPF/NPS employer-side balance at 60 if it is not already inside the Existing Corpus figure, so it is not double-counted.
A43: Total Expected Without New Investment | B43: =B41+B42 -> 31583805 | C43: ₹ | D43: Formula: FV of Existing Corpus + EPF
A44: RETIREMENT CORPUS GAP | B44: =MAX(0,B33-B43) -> 1.160773e+08 | C44: ₹ | D44: Formula: Total Corpus Required - Total Expected. This is the amount that new monthly investing has to create.
A46: E. HOW TO FUND THE GAP
A47: Parameter | B47: Value | C47: Unit | D47: Formula / Logic Used
A48: Option 1 - LEVEL Monthly SIP (never increased) | B48: =IF(B44=0,0,-PMT(B13/12,B10*12,0,B44)) -> 22545.181 | C48: ₹ p.m. | D48: Formula: -PMT(Blended Return/12, Years x 12, 0, Gap). The fixed monthly amount whose future value equals the gap. Negated because PMT returns outflows as negatives.
A49: Option 2 - STEP-UP SIP, year 1 monthly amount | B49: =IF(B44=0,0,IF(ABS(B13-B16)<0.0001,B44/(B10*(1+B13)^(B10-1))/12,B44*(B13-B16)/((1+B13)^B10-(1+B16)^B10)/12)) -> 8468.2705 | C49: ₹ p.m. | D49: Formula: Gap x (r - g) / ((1+r)^n - (1+g)^n) / 12, where r = blended return, g = step-up rate, n = years. Growing-annuity future value solved backwards for the first payment. Start lower, raise the SIP 10% each year as income grows.
A50: Option 3 - ONE-TIME Lumpsum Today | B50: =B44/(1+B13)^B10 -> 2940172.6 | C50: ₹ | D50: Formula: Gap / (1 + Blended Return) ^ Years. Present value of the gap - what a single investment today would have to be.
A51: Level SIP as % of Monthly Investible Surplus | B51: =IFERROR(B48/Inputs!B26,0) -> 0.17536927 | C51: % | D51: Formula: Level SIP / Monthly Surplus
A52: Step-Up SIP as % of Monthly Investible Surplus | B52: =IFERROR(B49/Inputs!B26,0) -> 0.065871035 | C52: % | D52: Formula: Step-Up SIP / Monthly Surplus. This is the recommended route - it matches rising income and frees cash today for the shorter goals.
A53: Total SIP over the whole accumulation period (step-up route) | B53: =IF(ABS(B16)<0.0001,B49*12*B10,B49*12*((1+B16)^B10-1)/B16) -> 30397040 | C53: ₹ | D53: Formula: Year-1 annual SIP x [((1+g)^n - 1) / g]. Sum of a geometric series - total money actually invested across 36 years.
A54: Wealth Created by Compounding | B54: =MAX(0,B44-B53) -> 85680255 | C54: ₹ | D54: Formula: Gap - Total Invested. The portion of the corpus that returns produced rather than the client's savings. At a 36-year horizon this is usually 80%+ of the total - the argument for starting at 24 rather than 34.
A56: F. THE COST OF DELAY
A57: Start Investing At Age | B57: Years of Compounding | C57: Step-Up SIP Needed (₹ p.m.) | D57: Formula / Logic Used
A58: =$B$7+0 -> 24 | B58: =$B$8-A58 -> 36 | C58: =IF(B58<=0,0,$B$44*($B$13-$B$16)/((1+$B$13)^B58-(1+$B$16)^B58)/12) -> 8468.2705 | D58: Same growing-annuity formula, only the number of years changes. The same target corpus, started later, costs dramatically more per month.
A59: =$B$7+3 -> 27 | B59: =$B$8-A59 -> 33 | C59: =IF(B59<=0,0,$B$44*($B$13-$B$16)/((1+$B$13)^B59-(1+$B$16)^B59)/12) -> 12426.84 | D59: Same growing-annuity formula, only the number of years changes. The same target corpus, started later, costs dramatically more per month.
A60: =$B$7+5 -> 29 | B60: =$B$8-A60 -> 31 | C60: =IF(B60<=0,0,$B$44*($B$13-$B$16)/((1+$B$13)^B60-(1+$B$16)^B60)/12) -> 16119.673 | D60: Same growing-annuity formula, only the number of years changes. The same target corpus, started later, costs dramatically more per month.
A61: =$B$7+10 -> 34 | B61: =$B$8-A61 -> 26 | C61: =IF(B61<=0,0,$B$44*($B$13-$B$16)/((1+$B$13)^B61-(1+$B$16)^B61)/12) -> 31500.947 | D61: Same growing-annuity formula, only the number of years changes. The same target corpus, started later, costs dramatically more per month.
A62: =$B$7+15 -> 39 | B62: =$B$8-A62 -> 21 | C62: =IF(B62<=0,0,$B$44*($B$13-$B$16)/((1+$B$13)^B62-(1+$B$16)^B62)/12) -> 63916.792 | D62: Same growing-annuity formula, only the number of years changes. The same target corpus, started later, costs dramatically more per month.
A64: CAVEAT: these are projections, not promises. A 12% equity assumption is a long-run average - real sequences include decade-long flat periods. Review the plan annually, re-run it whenever income, family size or goals change, and treat the corpus number as a direction of travel rather than a precise destination.

Sheet Projection
A1: 5. YEAR-BY-YEAR CORPUS PROJECTION (accumulation then drawdown)
A2: Fully formula-driven off the Inputs and Retirement sheets. Two built-in reconciliations: the closing corpus in the year before retirement should match the corpus requirement on the Retirement sheet almost exactly, and the balance surviving to life expectancy should be the medical buffer and legacy still compounding, because the living-expense portion is designed to be spent down to zero. If either check drifts, an assumption has been changed inconsistently.
A4: Year | B4: Age | C4: Phase | D4: Opening Corpus (₹) | E4: Annual Investment (₹) | F4: Annual Withdrawal (₹) | G4: Return Rate | H4: Growth (₹) | I4: Closing Corpus (₹) | J4: Closing in Today's Money (₹)
A5: 1 | B5: =IF(Inputs!$B$9+0>Inputs!$B$11,"",Inputs!$B$9+0) -> 24 | C5: =IF($B5>Inputs!$B$11,"",IF($B5<Inputs!$B$10,"Accumulation","Retirement")) -> Accumulation | D5: =IF($B5>Inputs!$B$11,"",Retirement!$B$40) -> 800000 | E5: =IF($B5>Inputs!$B$11,"",IF($B5>=Inputs!$B$10,0,Retirement!$B$49*12*(1+Inputs!$B$53)^(A5-1))) -> 101619.25 | F5: =IF($B5>Inputs!$B$11,"",IF($B5<Inputs!$B$10,0,Retirement!$B$23*(1+Inputs!$B$45)^($B5-Inputs!$B$10))) -> 0 | G5: =IF($B5>Inputs!$B$11,"",IF($B5<Inputs!$B$10,Inputs!$B$51,Inputs!$B$52)) -> 0.1075 | H5: =IF($B5>Inputs!$B$11,"",(D5-F5)*G5) -> 86000 | I5: =IF($B5>Inputs!$B$11,"",D5-F5+H5+E5) -> 987619.25 | J5: =IF($B5>Inputs!$B$11,"",I5/(1+Inputs!$B$45)^A5) -> 931716.27
A6: 2 | B6: =IF(Inputs!$B$9+1>Inputs!$B$11,"",Inputs!$B$9+1) -> 25 | C6: =IF($B6>Inputs!$B$11,"",IF($B6<Inputs!$B$10,"Accumulation","Retirement")) -> Accumulation | D6: =IF($B6>Inputs!$B$11,"",I5) -> 987619.25 | E6: =IF($B6>Inputs!$B$11,"",IF($B6>=Inputs!$B$10,0,Retirement!$B$49*12*(1+Inputs!$B$53)^(A6-1))) -> 111781.17 | F6: =IF($B6>Inputs!$B$11,"",IF($B6<Inputs!$B$10,0,Retirement!$B$23*(1+Inputs!$B$45)^($B6-Inputs!$B$10))) -> 0 | G6: =IF($B6>Inputs!$B$11,"",IF($B6<Inputs!$B$10,Inputs!$B$51,Inputs!$B$52)) -> 0.1075 | H6: =IF($B6>Inputs!$B$11,"",(D6-F6)*G6) -> 106169.07 | I6: =IF($B6>Inputs!$B$11,"",D6-F6+H6+E6) -> 1205569.5 | J6: =IF($B6>Inputs!$B$11,"",I6/(1+Inputs!$B$45)^A6) -> 1072952.5
A7: 3 | B7: =IF(Inputs!$B$9+2>Inputs!$B$11,"",Inputs!$B$9+2) -> 26 | C7: =IF($B7>Inputs!$B$11,"",IF($B7<Inputs!$B$10,"Accumulation","Retirement")) -> Accumulation | D7: =IF($B7>Inputs!$B$11,"",I6) -> 1205569.5 | E7: =IF($B7>Inputs!$B$11,"",IF($B7>=Inputs!$B$10,0,Retirement!$B$49*12*(1+Inputs!$B$53)^(A7-1))) -> 122959.29 | F7: =IF($B7>Inputs!$B$11,"",IF($B7<Inputs!$B$10,0,Retirement!$B$23*(1+Inputs!$B$45)^($B7-Inputs!$B$10))) -> 0 | G7: =IF($B7>Inputs!$B$11,"",IF($B7<Inputs!$B$10,Inputs!$B$51,Inputs!$B$52)) -> 0.1075 | H7: =IF($B7>Inputs!$B$11,"",(D7-F7)*G7) -> 129598.72 | I7: =IF($B7>Inputs!$B$11,"",D7-F7+H7+E7) -> 1458127.5 | J7: =IF($B7>Inputs!$B$11,"",I7/(1+Inputs!$B$45)^A7) -> 1224272
A8: 4 | B8: =IF(Inputs!$B$9+3>Inputs!$B$11,"",Inputs!$B$9+3) -> 27 | C8: =IF($B8>Inputs!$B$11,"",IF($B8<Inputs!$B$10,"Accumulation","Retirement")) -> Accumulation | D8: =IF($B8>Inputs!$B$11,"",I7) -> 1458127.5 | E8: =IF($B8>Inputs!$B$11,"",IF($B8>=Inputs!$B$10,0,Retirement!$B$49*12*(1+Inputs!$B$53)^(A8-1))) -> 135255.22 | F8: =IF($B8>Inputs!$B$11,"",IF($B8<Inputs!$B$10,0,Retirement!$B$23*(1+Inputs!$B$45)^($B8-Inputs!$B$10))) -> 0 | G8: =IF($B8>Inputs!$B$11,"",IF($B8<Inputs!$B$10,Inputs!$B$51,Inputs!$B$52)) -> 0.1075 | H8: =IF($B8>Inputs!$B$11,"",(D8-F8)*G8) -> 156748.71 | I8: =IF($B8>Inputs!$B$11,"",D8-F8+H8+E8) -> 1750131.4 | J8: =IF($B8>Inputs!$B$11,"",I8/(1+Inputs!$B$45)^A8) -> 1386268
A9: 5 | B9: =IF(Inputs!$B$9+4>Inputs!$B$11,"",Inputs!$B$9+4) -> 28 | C9: =IF($B9>Inputs!$B$11,"",IF($B9<Inputs!$B$10,"Accumulation","Retirement")) -> Accumulation | D9: =IF($B9>Inputs!$B$11,"",I8) -> 1750131.4 | E9: =IF($B9>Inputs!$B$11,"",IF($B9>=Inputs!$B$10,0,Retirement!$B$49*12*(1+Inputs!$B$53)^(A9-1))) -> 148780.74 | F9: =IF($B9>Inputs!$B$11,"",IF($B9<Inputs!$B$10,0,Retirement!$B$23*(1+Inputs!$B$45)^($B9-Inputs!$B$10))) -> 0 | G9: =IF($B9>Inputs!$B$11,"",IF($B9<Inputs!$B$10,Inputs!$B$51,Inputs!$B$52)) -> 0.1075 | H9: =IF($B9>Inputs!$B$11,"",(D9-F9)*G9) -> 188139.13 | I9: =IF($B9>Inputs!$B$11,"",D9-F9+H9+E9) -> 2087051.3 | J9: =IF($B9>Inputs!$B$11,"",I9/(1+Inputs!$B$45)^A9) -> 1559566.1
A10: 6 | B10: =IF(Inputs!$B$9+5>Inputs!$B$11,"",Inputs!$B$9+5) -> 29 | C10: =IF($B10>Inputs!$B$11,"",IF($B10<Inputs!$B$10,"Accumulation","Retirement")) -> Accumulation | D10: =IF($B10>Inputs!$B$11,"",I9) -> 2087051.3 | E10: =IF($B10>Inputs!$B$11,"",IF($B10>=Inputs!$B$10,0,Retirement!$B$49*12*(1+Inputs!$B$53)^(A10-1))) -> 163658.81 | F10: =IF($B10>Inputs!$B$11,"",IF($B10<Inputs!$B$10,0,Retirement!$B$23*(1+Inputs!$B$45)^($B10-Inputs!$B$10))) -> 0 | G10: =IF($B10>Inputs!$B$11,"",IF($B10<Inputs!$B$10,Inputs!$B$51,Inputs!$B$52)) -> 0.1075 | H10: =IF($B10>Inputs!$B$11,"",(D10-F10)*G10) -> 224358.01 | I10: =IF($B10>Inputs!$B$11,"",D10-F10+H10+E10) -> 2475068.1 | J10: =IF($B10>Inputs!$B$11,"",I10/(1+Inputs!$B$45)^A10) -> 1744825.3
A11: 7 | B11: =IF(Inputs!$B$9+6>Inputs!$B$11,"",Inputs!$B$9+6) -> 30 | C11: =IF($B11>Inputs!$B$11,"",IF($B11<Inputs!$B$10,"Accumulation","Retirement")) -> Accumulation | D11: =IF($B11>Inputs!$B$11,"",I10) -> 2475068.1 | E11: =IF($B11>Inputs!$B$11,"",IF($B11>=Inputs!$B$10,0,Retirement!$B$49*12*(1+Inputs!$B$53)^(A11-1))) -> 180024.69 | F11: =IF($B11>Inputs!$B$11,"",IF($B11<Inputs!$B$10,0,Retirement!$B$23*(1+Inputs!$B$45)^($B11-Inputs!$B$10))) -> 0 | G11: =IF($B11>Inputs!$B$11,"",IF($B11<Inputs!$B$10,Inputs!$B$51,Inputs!$B$52)) -> 0.1075 | H11: =IF($B11>Inputs!$B$11,"",(D11-F11)*G11) -> 266069.82 | I11: =IF($B11>Inputs!$B$11,"",D11-F11+H11+E11) -> 2921162.6 | J11: =IF($B11>Inputs!$B$11,"",I11/(1+Inputs!$B$45)^A11) -> 1942740
A12: 8 | B12: =IF(Inputs!$B$9+7>Inputs!$B$11,"",Inputs!$B$9+7) -> 31 | C12: =IF($B12>Inputs!$B$11,"",IF($B12<Inputs!$B$10,"Accumulation","Retirement")) -> Accumulation | D12: =IF($B12>Inputs!$B$11,"",I11) -> 2921162.6 | E12: =IF($B12>Inputs!$B$11,"",IF($B12>=Inputs!$B$10,0,Retirement!$B$49*12*(1+Inputs!$B$53)^(A12-1))) -> 198027.16 | F12: =IF($B12>Inputs!$B$11,"",IF($B12<Inputs!$B$10,0,Retirement!$B$23*(1+Inputs!$B$45)^($B12-Inputs!$B$10))) -> 0 | G12: =IF($B12>Inputs!$B$11,"",IF($B12<Inputs!$B$10,Inputs!$B$51,Inputs!$B$52)) -> 0.1075 | H12: =IF($B12>Inputs!$B$11,"",(D12-F12)*G12) -> 314024.98 | I12: =IF($B12>Inputs!$B$11,"",D12-F12+H12+E12) -> 3433214.8 | J12: =IF($B12>Inputs!$B$11,"",I12/(1+Inputs!$B$45)^A12) -> 2154041.4
A13: 9 | B13: =IF(Inputs!$B$9+8>Inputs!$B$11,"",Inputs!$B$9+8) -> 32 | C13: =IF($B13>Inputs!$B$11,"",IF($B13<Inputs!$B$10,"Accumulation","Retirement")) -> Accumulation | D13: =IF($B13>Inputs!$B$11,"",I12) -> 3433214.8 | E13: =IF($B13>Inputs!$B$11,"",IF($B13>=Inputs!$B$10,0,Retirement!$B$49*12*(1+Inputs!$B$53)^(A13-1))) -> 217829.88 | F13: =IF($B13>Inputs!$B$11,"",IF($B13<Inputs!$B$10,0,Retirement!$B$23*(1+Inputs!$B$45)^($B13-Inputs!$B$10))) -> 0 | G13: =IF($B13>Inputs!$B$11,"",IF($B13<Inputs!$B$10,Inputs!$B$51,Inputs!$B$52)) -> 0.1075 | H13: =IF($B13>Inputs!$B$11,"",(D13-F13)*G13) -> 369070.59 | I13: =IF($B13>Inputs!$B$11,"",D13-F13+H13+E13) -> 4020115.2 | J13: =IF($B13>Inputs!$B$11,"",I13/(1+Inputs!$B$45)^A13) -> 2379500
A14: 10 | B14: =IF(Inputs!$B$9+9>Inputs!$B$11,"",Inputs!$B$9+9) -> 33 | C14: =IF($B14>Inputs!$B$11,"",IF($B14<Inputs!$B$10,"Accumulation","Retirement")) -> Accumulation | D14: =IF($B14>Inputs!$B$11,"",I13) -> 4020115.2 | E14: =IF($B14>Inputs!$B$11,"",IF($B14>=Inputs!$B$10,0,Retirement!$B$49*12*(1+Inputs!$B$53)^(A14-1))) -> 239612.87 | F14: =IF($B14>Inputs!$B$11,"",IF($B14<Inputs!$B$10,0,Retirement!$B$23*(1+Inputs!$B$45)^($B14-Inputs!$B$10))) -> 0 | G14: =IF($B14>Inputs!$B$11,"",IF($B14<Inputs!$B$10,Inputs!$B$51,Inputs!$B$52)) -> 0.1075 | H14: =IF($B14>Inputs!$B$11,"",(D14-F14)*G14) -> 432162.39 | I14: =IF($B14>Inputs!$B$11,"",D14-F14+H14+E14) -> 4691890.5 | J14: =IF($B14>Inputs!$B$11,"",I14/(1+Inputs!$B$45)^A14) -> 2619927.1
A15: 11 | B15: =IF(Inputs!$B$9+10>Inputs!$B$11,"",Inputs!$B$9+10) -> 34 | C15: =IF($B15>Inputs!$B$11,"",IF($B15<Inputs!$B$10,"Accumulation","Retirement")) -> Accumulation | D15: =IF($B15>Inputs!$B$11,"",I14) -> 4691890.5 | E15: =IF($B15>Inputs!$B$11,"",IF($B15>=Inputs!$B$10,0,Retirement!$B$49*12*(1+Inputs!$B$53)^(A15-1))) -> 263574.15 | F15: =IF($B15>Inputs!$B$11,"",IF($B15<Inputs!$B$10,0,Retirement!$B$23*(1+Inputs!$B$45)^($B15-Inputs!$B$10))) -> 0 | G15: =IF($B15>Inputs!$B$11,"",IF($B15<Inputs!$B$10,Inputs!$B$51,Inputs!$B$52)) -> 0.1075 | H15: =IF($B15>Inputs!$B$11,"",(D15-F15)*G15) -> 504378.23 | I15: =IF($B15>Inputs!$B$11,"",D15-F15+H15+E15) -> 5459842.9 | J15: =IF($B15>Inputs!$B$11,"",I15/(1+Inputs!$B$45)^A15) -> 2876177.1
A16: 12 | B16: =IF(Inputs!$B$9+11>Inputs!$B$11,"",Inputs!$B$9+11) -> 35 | C16: =IF($B16>Inputs!$B$11,"",IF($B16<Inputs!$B$10,"Accumulation","Retirement")) -> Accumulation | D16: =IF($B16>Inputs!$B$11,"",I15) -> 5459842.9 | E16: =IF($B16>Inputs!$B$11,"",IF($B16>=Inputs!$B$10,0,Retirement!$B$49*12*(1+Inputs!$B$53)^(A16-1))) -> 289931.57 | F16: =IF($B16>Inputs!$B$11,"",IF($B16<Inputs!$B$10,0,Retirement!$B$23*(1+Inputs!$B$45)^($B16-Inputs!$B$10))) -> 0 | G16: =IF($B16>Inputs!$B$11,"",IF($B16<Inputs!$B$10,Inputs!$B$51,Inputs!$B$52)) -> 0.1075 | H16: =IF($B16>Inputs!$B$11,"",(D16-F16)*G16) -> 586933.11 | I16: =IF($B16>Inputs!$B$11,"",D16-F16+H16+E16) -> 6336707.5 | J16: =IF($B16>Inputs!$B$11,"",I16/(1+Inputs!$B$45)^A16) -> 3149149.5
A17: 13 | B17: =IF(Inputs!$B$9+12>Inputs!$B$11,"",Inputs!$B$9+12) -> 36 | C17: =IF($B17>Inputs!$B$11,"",IF($B17<Inputs!$B$10,"Accumulation","Retirement")) -> Accumulation | D17: =IF($B17>Inputs!$B$11,"",I16) -> 6336707.5 | E17: =IF($B17>Inputs!$B$11,"",IF($B17>=Inputs!$B$10,0,Retirement!$B$49*12*(1+Inputs!$B$53)^(A17-1))) -> 318924.72 | F17: =IF($B17>Inputs!$B$11,"",IF($B17<Inputs!$B$10,0,Retirement!$B$23*(1+Inputs!$B$45)^($B17-Inputs!$B$10))) -> 0 | G17: =IF($B17>Inputs!$B$11,"",IF($B17<Inputs!$B$10,Inputs!$B$51,Inputs!$B$52)) -> 0.1075 | H17: =IF($B17>Inputs!$B$11,"",(D17-F17)*G17) -> 681196.06 | I17: =IF($B17>Inputs!$B$11,"",D17-F17+H17+E17) -> 7336828.3 | J17: =IF($B17>Inputs!$B$11,"",I17/(1+Inputs!$B$45)^A17) -> 3439791.4
A18: 14 | B18: =IF(Inputs!$B$9+13>Inputs!$B$11,"",Inputs!$B$9+13) -> 37 | C18: =IF($B18>Inputs!$B$11,"",IF($B18<Inputs!$B$10,"Accumulation","Retirement")) -> Accumulation | D18: =IF($B18>Inputs!$B$11,"",I17) -> 7336828.3 | E18: =IF($B18>Inputs!$B$11,"",IF($B18>=Inputs!$B$10,0,Retirement!$B$49*12*(1+Inputs!$B$53)^(A18-1))) -> 350817.2 | F18: =IF($B18>Inputs!$B$11,"",IF($B18<Inputs!$B$10,0,Retirement!$B$23*(1+Inputs!$B$45)^($B18-Inputs!$B$10))) -> 0 | G18: =IF($B18>Inputs!$B$11,"",IF($B18<Inputs!$B$10,Inputs!$B$51,Inputs!$B$52)) -> 0.1075 | H18: =IF($B18>Inputs!$B$11,"",(D18-F18)*G18) -> 788709.04 | I18: =IF($B18>Inputs!$B$11,"",D18-F18+H18+E18) -> 8476354.6 | J18: =IF($B18>Inputs!$B$11,"",I18/(1+Inputs!$B$45)^A18) -> 3749099.8
A19: 15 | B19: =IF(Inputs!$B$9+14>Inputs!$B$11,"",Inputs!$B$9+14) -> 38 | C19: =IF($B19>Inputs!$B$11,"",IF($B19<Inputs!$B$10,"Accumulation","Retirement")) -> Accumulation | D19: =IF($B19>Inputs!$B$11,"",I18) -> 8476354.6 | E19: =IF($B19>Inputs!$B$11,"",IF($B19>=Inputs!$B$10,0,Retirement!$B$49*12*(1+Inputs!$B$53)^(A19-1))) -> 385898.92 | F19: =IF($B19>Inputs!$B$11,"",IF($B19<Inputs!$B$10,0,Retirement!$B$23*(1+Inputs!$B$45)^($B19-Inputs!$B$10))) -> 0 | G19: =IF($B19>Inputs!$B$11,"",IF($B19<Inputs!$B$10,Inputs!$B$51,Inputs!$B$52)) -> 0.1075 | H19: =IF($B19>Inputs!$B$11,"",(D19-F19)*G19) -> 911208.11 | I19: =IF($B19>Inputs!$B$11,"",D19-F19+H19+E19) -> 9773461.6 | J19: =IF($B19>Inputs!$B$11,"",I19/(1+Inputs!$B$45)^A19) -> 4078124
A20: 16 | B20: =IF(Inputs!$B$9+15>Inputs!$B$11,"",Inputs!$B$9+15) -> 39 | C20: =IF($B20>Inputs!$B$11,"",IF($B20<Inputs!$B$10,"Accumulation","Retirement")) -> Accumulation | D20: =IF($B20>Inputs!$B$11,"",I19) -> 9773461.6 | E20: =IF($B20>Inputs!$B$11,"",IF($B20>=Inputs!$B$10,0,Retirement!$B$49*12*(1+Inputs!$B$53)^(A20-1))) -> 424488.81 | F20: =IF($B20>Inputs!$B$11,"",IF($B20<Inputs!$B$10,0,Retirement!$B$23*(1+Inputs!$B$45)^($B20-Inputs!$B$10))) -> 0 | G20: =IF($B20>Inputs!$B$11,"",IF($B20<Inputs!$B$10,Inputs!$B$51,Inputs!$B$52)) -> 0.1075 | H20: =IF($B20>Inputs!$B$11,"",(D20-F20)*G20) -> 1050647.1 | I20: =IF($B20>Inputs!$B$11,"",D20-F20+H20+E20) -> 11248598 | J20: =IF($B20>Inputs!$B$11,"",I20/(1+Inputs!$B$45)^A20) -> 4427968.6
A21: 17 | B21: =IF(Inputs!$B$9+16>Inputs!$B$11,"",Inputs!$B$9+16) -> 40 | C21: =IF($B21>Inputs!$B$11,"",IF($B21<Inputs!$B$10,"Accumulation","Retirement")) -> Accumulation | D21: =IF($B21>Inputs!$B$11,"",I20) -> 11248598 | E21: =IF($B21>Inputs!$B$11,"",IF($B21>=Inputs!$B$10,0,Retirement!$B$49*12*(1+Inputs!$B$53)^(A21-1))) -> 466937.69 | F21: =IF($B21>Inputs!$B$11,"",IF($B21<Inputs!$B$10,0,Retirement!$B$23*(1+Inputs!$B$45)^($B21-Inputs!$B$10))) -> 0 | G21: =IF($B21>Inputs!$B$11,"",IF($B21<Inputs!$B$10,Inputs!$B$51,Inputs!$B$52)) -> 0.1075 | H21: =IF($B21>Inputs!$B$11,"",(D21-F21)*G21) -> 1209224.2 | I21: =IF($B21>Inputs!$B$11,"",D21-F21+H21+E21) -> 12924759 | J21: =IF($B21>Inputs!$B$11,"",I21/(1+Inputs!$B$45)^A21) -> 4799795.8
A22: 18 | B22: =IF(Inputs!$B$9+17>Inputs!$B$11,"",Inputs!$B$9+17) -> 41 | C22: =IF($B22>Inputs!$B$11,"",IF($B22<Inputs!$B$10,"Accumulation","Retirement")) -> Accumulation | D22: =IF($B22>Inputs!$B$11,"",I21) -> 12924759 | E22: =IF($B22>Inputs!$B$11,"",IF($B22>=Inputs!$B$10,0,Retirement!$B$49*12*(1+Inputs!$B$53)^(A22-1))) -> 513631.46 | F22: =IF($B22>Inputs!$B$11,"",IF($B22<Inputs!$B$10,0,Retirement!$B$23*(1+Inputs!$B$45)^($B22-Inputs!$B$10))) -> 0 | G22: =IF($B22>Inputs!$B$11,"",IF($B22<Inputs!$B$10,Inputs!$B$51,Inputs!$B$52)) -> 0.1075 | H22: =IF($B22>Inputs!$B$11,"",(D22-F22)*G22) -> 1389411.6 | I22: =IF($B22>Inputs!$B$11,"",D22-F22+H22+E22) -> 14827803 | J22: =IF($B22>Inputs!$B$11,"",I22/(1+Inputs!$B$45)^A22) -> 5194828.6
A23: 19 | B23: =IF(Inputs!$B$9+18>Inputs!$B$11,"",Inputs!$B$9+18) -> 42 | C23: =IF($B23>Inputs!$B$11,"",IF($B23<Inputs!$B$10,"Accumulation","Retirement")) -> Accumulation | D23: =IF($B23>Inputs!$B$11,"",I22) -> 14827803 | E23: =IF($B23>Inputs!$B$11,"",IF($B23>=Inputs!$B$10,0,Retirement!$B$49*12*(1+Inputs!$B$53)^(A23-1))) -> 564994.6 | F23: =IF($B23>Inputs!$B$11,"",IF($B23<Inputs!$B$10,0,Retirement!$B$23*(1+Inputs!$B$45)^($B23-Inputs!$B$10))) -> 0 | G23: =IF($B23>Inputs!$B$11,"",IF($B23<Inputs!$B$10,Inputs!$B$51,Inputs!$B$52)) -> 0.1075 | H23: =IF($B23>Inputs!$B$11,"",(D23-F23)*G23) -> 1593988.8 | I23: =IF($B23>Inputs!$B$11,"",D23-F23+H23+E23) -> 16986786 | J23: =IF($B23>Inputs!$B$11,"",I23/(1+Inputs!$B$45)^A23) -> 5614353.8
A24: 20 | B24: =IF(Inputs!$B$9+19>Inputs!$B$11,"",Inputs!$B$9+19) -> 43 | C24: =IF($B24>Inputs!$B$11,"",IF($B24<Inputs!$B$10,"Accumulation","Retirement")) -> Accumulation | D24: =IF($B24>Inputs!$B$11,"",I23) -> 16986786 | E24: =IF($B24>Inputs!$B$11,"",IF($B24>=Inputs!$B$10,0,Retirement!$B$49*12*(1+Inputs!$B$53)^(A24-1))) -> 621494.06 | F24: =IF($B24>Inputs!$B$11,"",IF($B24<Inputs!$B$10,0,Retirement!$B$23*(1+Inputs!$B$45)^($B24-Inputs!$B$10))) -> 0 | G24: =IF($B24>Inputs!$B$11,"",IF($B24<Inputs!$B$10,Inputs!$B$51,Inputs!$B$52)) -> 0.1075 | H24: =IF($B24>Inputs!$B$11,"",(D24-F24)*G24) -> 1826079.5 | I24: =IF($B24>Inputs!$B$11,"",D24-F24+H24+E24) -> 19434359 | J24: =IF($B24>Inputs!$B$11,"",I24/(1+Inputs!$B$45)^A24) -> 6059725.1
A25: 21 | B25: =IF(Inputs!$B$9+20>Inputs!$B$11,"",Inputs!$B$9+20) -> 44 | C25: =IF($B25>Inputs!$B$11,"",IF($B25<Inputs!$B$10,"Accumulation","Retirement")) -> Accumulation | D25: =IF($B25>Inputs!$B$11,"",I24) -> 19434359 | E25: =IF($B25>Inputs!$B$11,"",IF($B25>=Inputs!$B$10,0,Retirement!$B$49*12*(1+Inputs!$B$53)^(A25-1))) -> 683643.47 | F25: =IF($B25>Inputs!$B$11,"",IF($B25<Inputs!$B$10,0,Retirement!$B$23*(1+Inputs!$B$45)^($B25-Inputs!$B$10))) -> 0 | G25: =IF($B25>Inputs!$B$11,"",IF($B25<Inputs!$B$10,Inputs!$B$51,Inputs!$B$52)) -> 0.1075 | H25: =IF($B25>Inputs!$B$11,"",(D25-F25)*G25) -> 2089193.6 | I25: =IF($B25>Inputs!$B$11,"",D25-F25+H25+E25) -> 22207197 | J25: =IF($B25>Inputs!$B$11,"",I25/(1+Inputs!$B$45)^A25) -> 6532366.9
A26: 22 | B26: =IF(Inputs!$B$9+21>Inputs!$B$11,"",Inputs!$B$9+21) -> 45 | C26: =IF($B26>Inputs!$B$11,"",IF($B26<Inputs!$B$10,"Accumulation","Retirement")) -> Accumulation | D26: =IF($B26>Inputs!$B$11,"",I25) -> 22207197 | E26: =IF($B26>Inputs!$B$11,"",IF($B26>=Inputs!$B$10,0,Retirement!$B$49*12*(1+Inputs!$B$53)^(A26-1))) -> 752007.82 | F26: =IF($B26>Inputs!$B$11,"",IF($B26<Inputs!$B$10,0,Retirement!$B$23*(1+Inputs!$B$45)^($B26-Inputs!$B$10))) -> 0 | G26: =IF($B26>Inputs!$B$11,"",IF($B26<Inputs!$B$10,Inputs!$B$51,Inputs!$B$52)) -> 0.1075 | H26: =IF($B26>Inputs!$B$11,"",(D26-F26)*G26) -> 2387273.6 | I26: =IF($B26>Inputs!$B$11,"",D26-F26+H26+E26) -> 25346478 | J26: =IF($B26>Inputs!$B$11,"",I26/(1+Inputs!$B$45)^A26) -> 7033776.8
A27: 23 | B27: =IF(Inputs!$B$9+22>Inputs!$B$11,"",Inputs!$B$9+22) -> 46 | C27: =IF($B27>Inputs!$B$11,"",IF($B27<Inputs!$B$10,"Accumulation","Retirement")) -> Accumulation | D27: =IF($B27>Inputs!$B$11,"",I26) -> 25346478 | E27: =IF($B27>Inputs!$B$11,"",IF($B27>=Inputs!$B$10,0,Retirement!$B$49*12*(1+Inputs!$B$53)^(A27-1))) -> 827208.6 | F27: =IF($B27>Inputs!$B$11,"",IF($B27<Inputs!$B$10,0,Retirement!$B$23*(1+Inputs!$B$45)^($B27-Inputs!$B$10))) -> 0 | G27: =IF($B27>Inputs!$B$11,"",IF($B27<Inputs!$B$10,Inputs!$B$51,Inputs!$B$52)) -> 0.1075 | H27: =IF($B27>Inputs!$B$11,"",(D27-F27)*G27) -> 2724746.4 | I27: =IF($B27>Inputs!$B$11,"",D27-F27+H27+E27) -> 28898433 | J27: =IF($B27>Inputs!$B$11,"",I27/(1+Inputs!$B$45)^A27) -> 7565530.6
A28: 24 | B28: =IF(Inputs!$B$9+23>Inputs!$B$11,"",Inputs!$B$9+23) -> 47 | C28: =IF($B28>Inputs!$B$11,"",IF($B28<Inputs!$B$10,"Accumulation","Retirement")) -> Accumulation | D28: =IF($B28>Inputs!$B$11,"",I27) -> 28898433 | E28: =IF($B28>Inputs!$B$11,"",IF($B28>=Inputs!$B$10,0,Retirement!$B$49*12*(1+Inputs!$B$53)^(A28-1))) -> 909929.46 | F28: =IF($B28>Inputs!$B$11,"",IF($B28<Inputs!$B$10,0,Retirement!$B$23*(1+Inputs!$B$45)^($B28-Inputs!$B$10))) -> 0 | G28: =IF($B28>Inputs!$B$11,"",IF($B28<Inputs!$B$10,Inputs!$B$51,Inputs!$B$52)) -> 0.1075 | H28: =IF($B28>Inputs!$B$11,"",(D28-F28)*G28) -> 3106581.5 | I28: =IF($B28>Inputs!$B$11,"",D28-F28+H28+E28) -> 32914944 | J28: =IF($B28>Inputs!$B$11,"",I28/(1+Inputs!$B$45)^A28) -> 8129285.1
A29: 25 | B29: =IF(Inputs!$B$9+24>Inputs!$B$11,"",Inputs!$B$9+24) -> 48 | C29: =IF($B29>Inputs!$B$11,"",IF($B29<Inputs!$B$10,"Accumulation","Retirement")) -> Accumulation | D29: =IF($B29>Inputs!$B$11,"",I28) -> 32914944 | E29: =IF($B29>Inputs!$B$11,"",IF($B29>=Inputs!$B$10,0,Retirement!$B$49*12*(1+Inputs!$B$53)^(A29-1))) -> 1000922.4 | F29: =IF($B29>Inputs!$B$11,"",IF($B29<Inputs!$B$10,0,Retirement!$B$23*(1+Inputs!$B$45)^($B29-Inputs!$B$10))) -> 0 | G29: =IF($B29>Inputs!$B$11,"",IF($B29<Inputs!$B$10,Inputs!$B$51,Inputs!$B$52)) -> 0.1075 | H29: =IF($B29>Inputs!$B$11,"",(D29-F29)*G29) -> 3538356.5 | I29: =IF($B29>Inputs!$B$11,"",D29-F29+H29+E29) -> 37454223 | J29: =IF($B29>Inputs!$B$11,"",I29/(1+Inputs!$B$45)^A29) -> 8726782.6
A30: 26 | B30: =IF(Inputs!$B$9+25>Inputs!$B$11,"",Inputs!$B$9+25) -> 49 | C30: =IF($B30>Inputs!$B$11,"",IF($B30<Inputs!$B$10,"Accumulation","Retirement")) -> Accumulation | D30: =IF($B30>Inputs!$B$11,"",I29) -> 37454223 | E30: =IF($B30>Inputs!$B$11,"",IF($B30>=Inputs!$B$10,0,Retirement!$B$49*12*(1+Inputs!$B$53)^(A30-1))) -> 1101014.6 | F30: =IF($B30>Inputs!$B$11,"",IF($B30<Inputs!$B$10,0,Retirement!$B$23*(1+Inputs!$B$45)^($B30-Inputs!$B$10))) -> 0 | G30: =IF($B30>Inputs!$B$11,"",IF($B30<Inputs!$B$10,Inputs!$B$51,Inputs!$B$52)) -> 0.1075 | H30: =IF($B30>Inputs!$B$11,"",(D30-F30)*G30) -> 4026329 | I30: =IF($B30>Inputs!$B$11,"",D30-F30+H30+E30) -> 42581567 | J30: =IF($B30>Inputs!$B$11,"",I30/(1+Inputs!$B$45)^A30) -> 9359855.4
A31: 27 | B31: =IF(Inputs!$B$9+26>Inputs!$B$11,"",Inputs!$B$9+26) -> 50 | C31: =IF($B31>Inputs!$B$11,"",IF($B31<Inputs!$B$10,"Accumulation","Retirement")) -> Accumulation | D31: =IF($B31>Inputs!$B$11,"",I30) -> 42581567 | E31: =IF($B31>Inputs!$B$11,"",IF($B31>=Inputs!$B$10,0,Retirement!$B$49*12*(1+Inputs!$B$53)^(A31-1))) -> 1211116.1 | F31: =IF($B31>Inputs!$B$11,"",IF($B31<Inputs!$B$10,0,Retirement!$B$23*(1+Inputs!$B$45)^($B31-Inputs!$B$10))) -> 0 | G31: =IF($B31>Inputs!$B$11,"",IF($B31<Inputs!$B$10,Inputs!$B$51,Inputs!$B$52)) -> 0.1075 | H31: =IF($B31>Inputs!$B$11,"",(D31-F31)*G31) -> 4577518.4 | I31: =IF($B31>Inputs!$B$11,"",D31-F31+H31+E31) -> 48370201 | J31: =IF($B31>Inputs!$B$11,"",I31/(1+Inputs!$B$45)^A31) -> 10030430
A32: 28 | B32: =IF(Inputs!$B$9+27>Inputs!$B$11,"",Inputs!$B$9+27) -> 51 | C32: =IF($B32>Inputs!$B$11,"",IF($B32<Inputs!$B$10,"Accumulation","Retirement")) -> Accumulation | D32: =IF($B32>Inputs!$B$11,"",I31) -> 48370201 | E32: =IF($B32>Inputs!$B$11,"",IF($B32>=Inputs!$B$10,0,Retirement!$B$49*12*(1+Inputs!$B$53)^(A32-1))) -> 1332227.7 | F32: =IF($B32>Inputs!$B$11,"",IF($B32<Inputs!$B$10,0,Retirement!$B$23*(1+Inputs!$B$45)^($B32-Inputs!$B$10))) -> 0 | G32: =IF($B32>Inputs!$B$11,"",IF($B32<Inputs!$B$10,Inputs!$B$51,Inputs!$B$52)) -> 0.1075 | H32: =IF($B32>Inputs!$B$11,"",(D32-F32)*G32) -> 5199796.6 | I32: =IF($B32>Inputs!$B$11,"",D32-F32+H32+E32) -> 54902225 | J32: =IF($B32>Inputs!$B$11,"",I32/(1+Inputs!$B$45)^A32) -> 10740530
A33: 29 | B33: =IF(Inputs!$B$9+28>Inputs!$B$11,"",Inputs!$B$9+28) -> 52 | C33: =IF($B33>Inputs!$B$11,"",IF($B33<Inputs!$B$10,"Accumulation","Retirement")) -> Accumulation | D33: =IF($B33>Inputs!$B$11,"",I32) -> 54902225 | E33: =IF($B33>Inputs!$B$11,"",IF($B33>=Inputs!$B$10,0,Retirement!$B$49*12*(1+Inputs!$B$53)^(A33-1))) -> 1465450.5 | F33: =IF($B33>Inputs!$B$11,"",IF($B33<Inputs!$B$10,0,Retirement!$B$23*(1+Inputs!$B$45)^($B33-Inputs!$B$10))) -> 0 | G33: =IF($B33>Inputs!$B$11,"",IF($B33<Inputs!$B$10,Inputs!$B$51,Inputs!$B$52)) -> 0.1075 | H33: =IF($B33>Inputs!$B$11,"",(D33-F33)*G33) -> 5901989.2 | I33: =IF($B33>Inputs!$B$11,"",D33-F33+H33+E33) -> 62269665 | J33: =IF($B33>Inputs!$B$11,"",I33/(1+Inputs!$B$45)^A33) -> 11492286
A34: 30 | B34: =IF(Inputs!$B$9+29>Inputs!$B$11,"",Inputs!$B$9+29) -> 53 | C34: =IF($B34>Inputs!$B$11,"",IF($B34<Inputs!$B$10,"Accumulation","Retirement")) -> Accumulation | D34: =IF($B34>Inputs!$B$11,"",I33) -> 62269665 | E34: =IF($B34>Inputs!$B$11,"",IF($B34>=Inputs!$B$10,0,Retirement!$B$49*12*(1+Inputs!$B$53)^(A34-1))) -> 1611995.5 | F34: =IF($B34>Inputs!$B$11,"",IF($B34<Inputs!$B$10,0,Retirement!$B$23*(1+Inputs!$B$45)^($B34-Inputs!$B$10))) -> 0 | G34: =IF($B34>Inputs!$B$11,"",IF($B34<Inputs!$B$10,Inputs!$B$51,Inputs!$B$52)) -> 0.1075 | H34: =IF($B34>Inputs!$B$11,"",(D34-F34)*G34) -> 6693989 | I34: =IF($B34>Inputs!$B$11,"",D34-F34+H34+E34) -> 70575650 | J34: =IF($B34>Inputs!$B$11,"",I34/(1+Inputs!$B$45)^A34) -> 12287936
A35: 31 | B35: =IF(Inputs!$B$9+30>Inputs!$B$11,"",Inputs!$B$9+30) -> 54 | C35: =IF($B35>Inputs!$B$11,"",IF($B35<Inputs!$B$10,"Accumulation","Retirement")) -> Accumulation | D35: =IF($B35>Inputs!$B$11,"",I34) -> 70575650 | E35: =IF($B35>Inputs!$B$11,"",IF($B35>=Inputs!$B$10,0,Retirement!$B$49*12*(1+Inputs!$B$53)^(A35-1))) -> 1773195.1 | F35: =IF($B35>Inputs!$B$11,"",IF($B35<Inputs!$B$10,0,Retirement!$B$23*(1+Inputs!$B$45)^($B35-Inputs!$B$10))) -> 0 | G35: =IF($B35>Inputs!$B$11,"",IF($B35<Inputs!$B$10,Inputs!$B$51,Inputs!$B$52)) -> 0.1075 | H35: =IF($B35>Inputs!$B$11,"",(D35-F35)*G35) -> 7586882.3 | I35: =IF($B35>Inputs!$B$11,"",D35-F35+H35+E35) -> 79935727 | J35: =IF($B35>Inputs!$B$11,"",I35/(1+Inputs!$B$45)^A35) -> 13129830
A36: 32 | B36: =IF(Inputs!$B$9+31>Inputs!$B$11,"",Inputs!$B$9+31) -> 55 | C36: =IF($B36>Inputs!$B$11,"",IF($B36<Inputs!$B$10,"Accumulation","Retirement")) -> Accumulation | D36: =IF($B36>Inputs!$B$11,"",I35) -> 79935727 | E36: =IF($B36>Inputs!$B$11,"",IF($B36>=Inputs!$B$10,0,Retirement!$B$49*12*(1+Inputs!$B$53)^(A36-1))) -> 1950514.6 | F36: =IF($B36>Inputs!$B$11,"",IF($B36<Inputs!$B$10,0,Retirement!$B$23*(1+Inputs!$B$45)^($B36-Inputs!$B$10))) -> 0 | G36: =IF($B36>Inputs!$B$11,"",IF($B36<Inputs!$B$10,Inputs!$B$51,Inputs!$B$52)) -> 0.1075 | H36: =IF($B36>Inputs!$B$11,"",(D36-F36)*G36) -> 8593090.7 | I36: =IF($B36>Inputs!$B$11,"",D36-F36+H36+E36) -> 90479332 | J36: =IF($B36>Inputs!$B$11,"",I36/(1+Inputs!$B$45)^A36) -> 14020442
A37: 33 | B37: =IF(Inputs!$B$9+32>Inputs!$B$11,"",Inputs!$B$9+32) -> 56 | C37: =IF($B37>Inputs!$B$11,"",IF($B37<Inputs!$B$10,"Accumulation","Retirement")) -> Accumulation | D37: =IF($B37>Inputs!$B$11,"",I36) -> 90479332 | E37: =IF($B37>Inputs!$B$11,"",IF($B37>=Inputs!$B$10,0,Retirement!$B$49*12*(1+Inputs!$B$53)^(A37-1))) -> 2145566.1 | F37: =IF($B37>Inputs!$B$11,"",IF($B37<Inputs!$B$10,0,Retirement!$B$23*(1+Inputs!$B$45)^($B37-Inputs!$B$10))) -> 0 | G37: =IF($B37>Inputs!$B$11,"",IF($B37<Inputs!$B$10,Inputs!$B$51,Inputs!$B$52)) -> 0.1075 | H37: =IF($B37>Inputs!$B$11,"",(D37-F37)*G37) -> 9726528.2 | I37: =IF($B37>Inputs!$B$11,"",D37-F37+H37+E37) -> 1.0235143e+08 | J37: =IF($B37>Inputs!$B$11,"",I37/(1+Inputs!$B$45)^A37) -> 14962369
A38: 34 | B38: =IF(Inputs!$B$9+33>Inputs!$B$11,"",Inputs!$B$9+33) -> 57 | C38: =IF($B38>Inputs!$B$11,"",IF($B38<Inputs!$B$10,"Accumulation","Retirement")) -> Accumulation | D38: =IF($B38>Inputs!$B$11,"",I37) -> 1.0235143e+08 | E38: =IF($B38>Inputs!$B$11,"",IF($B38>=Inputs!$B$10,0,Retirement!$B$49*12*(1+Inputs!$B$53)^(A38-1))) -> 2360122.7 | F38: =IF($B38>Inputs!$B$11,"",IF($B38<Inputs!$B$10,0,Retirement!$B$23*(1+Inputs!$B$45)^($B38-Inputs!$B$10))) -> 0 | G38: =IF($B38>Inputs!$B$11,"",IF($B38<Inputs!$B$10,Inputs!$B$51,Inputs!$B$52)) -> 0.1075 | H38: =IF($B38>Inputs!$B$11,"",(D38-F38)*G38) -> 11002778 | I38: =IF($B38>Inputs!$B$11,"",D38-F38+H38+E38) -> 1.1571433e+08 | J38: =IF($B38>Inputs!$B$11,"",I38/(1+Inputs!$B$45)^A38) -> 15958340
A39: 35 | B39: =IF(Inputs!$B$9+34>Inputs!$B$11,"",Inputs!$B$9+34) -> 58 | C39: =IF($B39>Inputs!$B$11,"",IF($B39<Inputs!$B$10,"Accumulation","Retirement")) -> Accumulation | D39: =IF($B39>Inputs!$B$11,"",I38) -> 1.1571433e+08 | E39: =IF($B39>Inputs!$B$11,"",IF($B39>=Inputs!$B$10,0,Retirement!$B$49*12*(1+Inputs!$B$53)^(A39-1))) -> 2596134.9 | F39: =IF($B39>Inputs!$B$11,"",IF($B39<Inputs!$B$10,0,Retirement!$B$23*(1+Inputs!$B$45)^($B39-Inputs!$B$10))) -> 0 | G39: =IF($B39>Inputs!$B$11,"",IF($B39<Inputs!$B$10,Inputs!$B$51,Inputs!$B$52)) -> 0.1075 | H39: =IF($B39>Inputs!$B$11,"",(D39-F39)*G39) -> 12439290 | I39: =IF($B39>Inputs!$B$11,"",D39-F39+H39+E39) -> 1.3074975e+08 | J39: =IF($B39>Inputs!$B$11,"",I39/(1+Inputs!$B$45)^A39) -> 17011225
A40: 36 | B40: =IF(Inputs!$B$9+35>Inputs!$B$11,"",Inputs!$B$9+35) -> 59 | C40: =IF($B40>Inputs!$B$11,"",IF($B40<Inputs!$B$10,"Accumulation","Retirement")) -> Accumulation | D40: =IF($B40>Inputs!$B$11,"",I39) -> 1.3074975e+08 | E40: =IF($B40>Inputs!$B$11,"",IF($B40>=Inputs!$B$10,0,Retirement!$B$49*12*(1+Inputs!$B$53)^(A40-1))) -> 2855748.4 | F40: =IF($B40>Inputs!$B$11,"",IF($B40<Inputs!$B$10,0,Retirement!$B$23*(1+Inputs!$B$45)^($B40-Inputs!$B$10))) -> 0 | G40: =IF($B40>Inputs!$B$11,"",IF($B40<Inputs!$B$10,Inputs!$B$51,Inputs!$B$52)) -> 0.1075 | H40: =IF($B40>Inputs!$B$11,"",(D40-F40)*G40) -> 14055598 | I40: =IF($B40>Inputs!$B$11,"",D40-F40+H40+E40) -> 1.476611e+08 | J40: =IF($B40>Inputs!$B$11,"",I40/(1+Inputs!$B$45)^A40) -> 18124037
A41: 37 | B41: =IF(Inputs!$B$9+36>Inputs!$B$11,"",Inputs!$B$9+36) -> 60 | C41: =IF($B41>Inputs!$B$11,"",IF($B41<Inputs!$B$10,"Accumulation","Retirement")) -> Retirement | D41: =IF($B41>Inputs!$B$11,"",I40) -> 1.476611e+08 | E41: =IF($B41>Inputs!$B$11,"",IF($B41>=Inputs!$B$10,0,Retirement!$B$49*12*(1+Inputs!$B$53)^(A41-1))) -> 0 | F41: =IF($B41>Inputs!$B$11,"",IF($B41<Inputs!$B$10,0,Retirement!$B$23*(1+Inputs!$B$45)^($B41-Inputs!$B$10))) -> 5499395.1 | G41: =IF($B41>Inputs!$B$11,"",IF($B41<Inputs!$B$10,Inputs!$B$51,Inputs!$B$52)) -> 0.075 | H41: =IF($B41>Inputs!$B$11,"",(D41-F41)*G41) -> 10662128 | I41: =IF($B41>Inputs!$B$11,"",D41-F41+H41+E41) -> 1.5282383e+08 | J41: =IF($B41>Inputs!$B$11,"",I41/(1+Inputs!$B$45)^A41) -> 17695958
A42: 38 | B42: =IF(Inputs!$B$9+37>Inputs!$B$11,"",Inputs!$B$9+37) -> 61 | C42: =IF($B42>Inputs!$B$11,"",IF($B42<Inputs!$B$10,"Accumulation","Retirement")) -> Retirement | D42: =IF($B42>Inputs!$B$11,"",I41) -> 1.5282383e+08 | E42: =IF($B42>Inputs!$B$11,"",IF($B42>=Inputs!$B$10,0,Retirement!$B$49*12*(1+Inputs!$B$53)^(A42-1))) -> 0 | F42: =IF($B42>Inputs!$B$11,"",IF($B42<Inputs!$B$10,0,Retirement!$B$23*(1+Inputs!$B$45)^($B42-Inputs!$B$10))) -> 5829358.8 | G42: =IF($B42>Inputs!$B$11,"",IF($B42<Inputs!$B$10,Inputs!$B$51,Inputs!$B$52)) -> 0.075 | H42: =IF($B42>Inputs!$B$11,"",(D42-F42)*G42) -> 11024586 | I42: =IF($B42>Inputs!$B$11,"",D42-F42+H42+E42) -> 1.5801906e+08 | J42: =IF($B42>Inputs!$B$11,"",I42/(1+Inputs!$B$45)^A42) -> 17261820
A43: 39 | B43: =IF(Inputs!$B$9+38>Inputs!$B$11,"",Inputs!$B$9+38) -> 62 | C43: =IF($B43>Inputs!$B$11,"",IF($B43<Inputs!$B$10,"Accumulation","Retirement")) -> Retirement | D43: =IF($B43>Inputs!$B$11,"",I42) -> 1.5801906e+08 | E43: =IF($B43>Inputs!$B$11,"",IF($B43>=Inputs!$B$10,0,Retirement!$B$49*12*(1+Inputs!$B$53)^(A43-1))) -> 0 | F43: =IF($B43>Inputs!$B$11,"",IF($B43<Inputs!$B$10,0,Retirement!$B$23*(1+Inputs!$B$45)^($B43-Inputs!$B$10))) -> 6179120.3 | G43: =IF($B43>Inputs!$B$11,"",IF($B43<Inputs!$B$10,Inputs!$B$51,Inputs!$B$52)) -> 0.075 | H43: =IF($B43>Inputs!$B$11,"",(D43-F43)*G43) -> 11387995 | I43: =IF($B43>Inputs!$B$11,"",D43-F43+H43+E43) -> 1.6322793e+08 | J43: =IF($B43>Inputs!$B$11,"",I43/(1+Inputs!$B$45)^A43) -> 16821539
A44: 40 | B44: =IF(Inputs!$B$9+39>Inputs!$B$11,"",Inputs!$B$9+39) -> 63 | C44: =IF($B44>Inputs!$B$11,"",IF($B44<Inputs!$B$10,"Accumulation","Retirement")) -> Retirement | D44: =IF($B44>Inputs!$B$11,"",I43) -> 1.6322793e+08 | E44: =IF($B44>Inputs!$B$11,"",IF($B44>=Inputs!$B$10,0,Retirement!$B$49*12*(1+Inputs!$B$53)^(A44-1))) -> 0 | F44: =IF($B44>Inputs!$B$11,"",IF($B44<Inputs!$B$10,0,Retirement!$B$23*(1+Inputs!$B$45)^($B44-Inputs!$B$10))) -> 6549867.6 | G44: =IF($B44>Inputs!$B$11,"",IF($B44<Inputs!$B$10,Inputs!$B$51,Inputs!$B$52)) -> 0.075 | H44: =IF($B44>Inputs!$B$11,"",(D44-F44)*G44) -> 11750855 | I44: =IF($B44>Inputs!$B$11,"",D44-F44+H44+E44) -> 1.6842892e+08 | J44: =IF($B44>Inputs!$B$11,"",I44/(1+Inputs!$B$45)^A44) -> 16375028
A45: 41 | B45: =IF(Inputs!$B$9+40>Inputs!$B$11,"",Inputs!$B$9+40) -> 64 | C45: =IF($B45>Inputs!$B$11,"",IF($B45<Inputs!$B$10,"Accumulation","Retirement")) -> Retirement | D45: =IF($B45>Inputs!$B$11,"",I44) -> 1.6842892e+08 | E45: =IF($B45>Inputs!$B$11,"",IF($B45>=Inputs!$B$10,0,Retirement!$B$49*12*(1+Inputs!$B$53)^(A45-1))) -> 0 | F45: =IF($B45>Inputs!$B$11,"",IF($B45<Inputs!$B$10,0,Retirement!$B$23*(1+Inputs!$B$45)^($B45-Inputs!$B$10))) -> 6942859.6 | G45: =IF($B45>Inputs!$B$11,"",IF($B45<Inputs!$B$10,Inputs!$B$51,Inputs!$B$52)) -> 0.075 | H45: =IF($B45>Inputs!$B$11,"",(D45-F45)*G45) -> 12111455 | I45: =IF($B45>Inputs!$B$11,"",D45-F45+H45+E45) -> 1.7359752e+08 | J45: =IF($B45>Inputs!$B$11,"",I45/(1+Inputs!$B$45)^A45) -> 15922198
A46: 42 | B46: =IF(Inputs!$B$9+41>Inputs!$B$11,"",Inputs!$B$9+41) -> 65 | C46: =IF($B46>Inputs!$B$11,"",IF($B46<Inputs!$B$10,"Accumulation","Retirement")) -> Retirement | D46: =IF($B46>Inputs!$B$11,"",I45) -> 1.7359752e+08 | E46: =IF($B46>Inputs!$B$11,"",IF($B46>=Inputs!$B$10,0,Retirement!$B$49*12*(1+Inputs!$B$53)^(A46-1))) -> 0 | F46: =IF($B46>Inputs!$B$11,"",IF($B46<Inputs!$B$10,0,Retirement!$B$23*(1+Inputs!$B$45)^($B46-Inputs!$B$10))) -> 7359431.2 | G46: =IF($B46>Inputs!$B$11,"",IF($B46<Inputs!$B$10,Inputs!$B$51,Inputs!$B$52)) -> 0.075 | H46: =IF($B46>Inputs!$B$11,"",(D46-F46)*G46) -> 12467856 | I46: =IF($B46>Inputs!$B$11,"",D46-F46+H46+E46) -> 1.7870594e+08 | J46: =IF($B46>Inputs!$B$11,"",I46/(1+Inputs!$B$45)^A46) -> 15462961
A47: 43 | B47: =IF(Inputs!$B$9+42>Inputs!$B$11,"",Inputs!$B$9+42) -> 66 | C47: =IF($B47>Inputs!$B$11,"",IF($B47<Inputs!$B$10,"Accumulation","Retirement")) -> Retirement | D47: =IF($B47>Inputs!$B$11,"",I46) -> 1.7870594e+08 | E47: =IF($B47>Inputs!$B$11,"",IF($B47>=Inputs!$B$10,0,Retirement!$B$49*12*(1+Inputs!$B$53)^(A47-1))) -> 0 | F47: =IF($B47>Inputs!$B$11,"",IF($B47<Inputs!$B$10,0,Retirement!$B$23*(1+Inputs!$B$45)^($B47-Inputs!$B$10))) -> 7800997.1 | G47: =IF($B47>Inputs!$B$11,"",IF($B47<Inputs!$B$10,Inputs!$B$51,Inputs!$B$52)) -> 0.075 | H47: =IF($B47>Inputs!$B$11,"",(D47-F47)*G47) -> 12817871 | I47: =IF($B47>Inputs!$B$11,"",D47-F47+H47+E47) -> 1.8372282e+08 | J47: =IF($B47>Inputs!$B$11,"",I47/(1+Inputs!$B$45)^A47) -> 14997224
A48: 44 | B48: =IF(Inputs!$B$9+43>Inputs!$B$11,"",Inputs!$B$9+43) -> 67 | C48: =IF($B48>Inputs!$B$11,"",IF($B48<Inputs!$B$10,"Accumulation","Retirement")) -> Retirement | D48: =IF($B48>Inputs!$B$11,"",I47) -> 1.8372282e+08 | E48: =IF($B48>Inputs!$B$11,"",IF($B48>=Inputs!$B$10,0,Retirement!$B$49*12*(1+Inputs!$B$53)^(A48-1))) -> 0 | F48: =IF($B48>Inputs!$B$11,"",IF($B48<Inputs!$B$10,0,Retirement!$B$23*(1+Inputs!$B$45)^($B48-Inputs!$B$10))) -> 8269056.9 | G48: =IF($B48>Inputs!$B$11,"",IF($B48<Inputs!$B$10,Inputs!$B$51,Inputs!$B$52)) -> 0.075 | H48: =IF($B48>Inputs!$B$11,"",(D48-F48)*G48) -> 13159032 | I48: =IF($B48>Inputs!$B$11,"",D48-F48+H48+E48) -> 1.8861279e+08 | J48: =IF($B48>Inputs!$B$11,"",I48/(1+Inputs!$B$45)^A48) -> 14524897
A49: 45 | B49: =IF(Inputs!$B$9+44>Inputs!$B$11,"",Inputs!$B$9+44) -> 68 | C49: =IF($B49>Inputs!$B$11,"",IF($B49<Inputs!$B$10,"Accumulation","Retirement")) -> Retirement | D49: =IF($B49>Inputs!$B$11,"",I48) -> 1.8861279e+08 | E49: =IF($B49>Inputs!$B$11,"",IF($B49>=Inputs!$B$10,0,Retirement!$B$49*12*(1+Inputs!$B$53)^(A49-1))) -> 0 | F49: =IF($B49>Inputs!$B$11,"",IF($B49<Inputs!$B$10,0,Retirement!$B$23*(1+Inputs!$B$45)^($B49-Inputs!$B$10))) -> 8765200.3 | G49: =IF($B49>Inputs!$B$11,"",IF($B49<Inputs!$B$10,Inputs!$B$51,Inputs!$B$52)) -> 0.075 | H49: =IF($B49>Inputs!$B$11,"",(D49-F49)*G49) -> 13488569 | I49: =IF($B49>Inputs!$B$11,"",D49-F49+H49+E49) -> 1.9333616e+08 | J49: =IF($B49>Inputs!$B$11,"",I49/(1+Inputs!$B$45)^A49) -> 14045886
A50: 46 | B50: =IF(Inputs!$B$9+45>Inputs!$B$11,"",Inputs!$B$9+45) -> 69 | C50: =IF($B50>Inputs!$B$11,"",IF($B50<Inputs!$B$10,"Accumulation","Retirement")) -> Retirement | D50: =IF($B50>Inputs!$B$11,"",I49) -> 1.9333616e+08 | E50: =IF($B50>Inputs!$B$11,"",IF($B50>=Inputs!$B$10,0,Retirement!$B$49*12*(1+Inputs!$B$53)^(A50-1))) -> 0 | F50: =IF($B50>Inputs!$B$11,"",IF($B50<Inputs!$B$10,0,Retirement!$B$23*(1+Inputs!$B$45)^($B50-Inputs!$B$10))) -> 9291112.3 | G50: =IF($B50>Inputs!$B$11,"",IF($B50<Inputs!$B$10,Inputs!$B$51,Inputs!$B$52)) -> 0.075 | H50: =IF($B50>Inputs!$B$11,"",(D50-F50)*G50) -> 13803379 | I50: =IF($B50>Inputs!$B$11,"",D50-F50+H50+E50) -> 1.9784843e+08 | J50: =IF($B50>Inputs!$B$11,"",I50/(1+Inputs!$B$45)^A50) -> 13560097
A51: 47 | B51: =IF(Inputs!$B$9+46>Inputs!$B$11,"",Inputs!$B$9+46) -> 70 | C51: =IF($B51>Inputs!$B$11,"",IF($B51<Inputs!$B$10,"Accumulation","Retirement")) -> Retirement | D51: =IF($B51>Inputs!$B$11,"",I50) -> 1.9784843e+08 | E51: =IF($B51>Inputs!$B$11,"",IF($B51>=Inputs!$B$10,0,Retirement!$B$49*12*(1+Inputs!$B$53)^(A51-1))) -> 0 | F51: =IF($B51>Inputs!$B$11,"",IF($B51<Inputs!$B$10,0,Retirement!$B$23*(1+Inputs!$B$45)^($B51-Inputs!$B$10))) -> 9848579 | G51: =IF($B51>Inputs!$B$11,"",IF($B51<Inputs!$B$10,Inputs!$B$51,Inputs!$B$52)) -> 0.075 | H51: =IF($B51>Inputs!$B$11,"",(D51-F51)*G51) -> 14099989 | I51: =IF($B51>Inputs!$B$11,"",D51-F51+H51+E51) -> 2.0209984e+08 | J51: =IF($B51>Inputs!$B$11,"",I51/(1+Inputs!$B$45)^A51) -> 13067433
A52: 48 | B52: =IF(Inputs!$B$9+47>Inputs!$B$11,"",Inputs!$B$9+47) -> 71 | C52: =IF($B52>Inputs!$B$11,"",IF($B52<Inputs!$B$10,"Accumulation","Retirement")) -> Retirement | D52: =IF($B52>Inputs!$B$11,"",I51) -> 2.0209984e+08 | E52: =IF($B52>Inputs!$B$11,"",IF($B52>=Inputs!$B$10,0,Retirement!$B$49*12*(1+Inputs!$B$53)^(A52-1))) -> 0 | F52: =IF($B52>Inputs!$B$11,"",IF($B52<Inputs!$B$10,0,Retirement!$B$23*(1+Inputs!$B$45)^($B52-Inputs!$B$10))) -> 10439494 | G52: =IF($B52>Inputs!$B$11,"",IF($B52<Inputs!$B$10,Inputs!$B$51,Inputs!$B$52)) -> 0.075 | H52: =IF($B52>Inputs!$B$11,"",(D52-F52)*G52) -> 14374526 | I52: =IF($B52>Inputs!$B$11,"",D52-F52+H52+E52) -> 2.0603487e+08 | J52: =IF($B52>Inputs!$B$11,"",I52/(1+Inputs!$B$45)^A52) -> 12567798
A53: 49 | B53: =IF(Inputs!$B$9+48>Inputs!$B$11,"",Inputs!$B$9+48) -> 72 | C53: =IF($B53>Inputs!$B$11,"",IF($B53<Inputs!$B$10,"Accumulation","Retirement")) -> Retirement | D53: =IF($B53>Inputs!$B$11,"",I52) -> 2.0603487e+08 | E53: =IF($B53>Inputs!$B$11,"",IF($B53>=Inputs!$B$10,0,Retirement!$B$49*12*(1+Inputs!$B$53)^(A53-1))) -> 0 | F53: =IF($B53>Inputs!$B$11,"",IF($B53<Inputs!$B$10,0,Retirement!$B$23*(1+Inputs!$B$45)^($B53-Inputs!$B$10))) -> 11065863 | G53: =IF($B53>Inputs!$B$11,"",IF($B53<Inputs!$B$10,Inputs!$B$51,Inputs!$B$52)) -> 0.075 | H53: =IF($B53>Inputs!$B$11,"",(D53-F53)*G53) -> 14622675 | I53: =IF($B53>Inputs!$B$11,"",D53-F53+H53+E53) -> 2.0959168e+08 | J53: =IF($B53>Inputs!$B$11,"",I53/(1+Inputs!$B$45)^A53) -> 12061092
A54: 50 | B54: =IF(Inputs!$B$9+49>Inputs!$B$11,"",Inputs!$B$9+49) -> 73 | C54: =IF($B54>Inputs!$B$11,"",IF($B54<Inputs!$B$10,"Accumulation","Retirement")) -> Retirement | D54: =IF($B54>Inputs!$B$11,"",I53) -> 2.0959168e+08 | E54: =IF($B54>Inputs!$B$11,"",IF($B54>=Inputs!$B$10,0,Retirement!$B$49*12*(1+Inputs!$B$53)^(A54-1))) -> 0 | F54: =IF($B54>Inputs!$B$11,"",IF($B54<Inputs!$B$10,0,Retirement!$B$23*(1+Inputs!$B$45)^($B54-Inputs!$B$10))) -> 11729815 | G54: =IF($B54>Inputs!$B$11,"",IF($B54<Inputs!$B$10,Inputs!$B$51,Inputs!$B$52)) -> 0.075 | H54: =IF($B54>Inputs!$B$11,"",(D54-F54)*G54) -> 14839640 | I54: =IF($B54>Inputs!$B$11,"",D54-F54+H54+E54) -> 2.127015e+08 | J54: =IF($B54>Inputs!$B$11,"",I54/(1+Inputs!$B$45)^A54) -> 11547216
A55: 51 | B55: =IF(Inputs!$B$9+50>Inputs!$B$11,"",Inputs!$B$9+50) -> 74 | C55: =IF($B55>Inputs!$B$11,"",IF($B55<Inputs!$B$10,"Accumulation","Retirement")) -> Retirement | D55: =IF($B55>Inputs!$B$11,"",I54) -> 2.127015e+08 | E55: =IF($B55>Inputs!$B$11,"",IF($B55>=Inputs!$B$10,0,Retirement!$B$49*12*(1+Inputs!$B$53)^(A55-1))) -> 0 | F55: =IF($B55>Inputs!$B$11,"",IF($B55<Inputs!$B$10,0,Retirement!$B$23*(1+Inputs!$B$45)^($B55-Inputs!$B$10))) -> 12433604 | G55: =IF($B55>Inputs!$B$11,"",IF($B55<Inputs!$B$10,Inputs!$B$51,Inputs!$B$52)) -> 0.075 | H55: =IF($B55>Inputs!$B$11,"",(D55-F55)*G55) -> 15020092 | I55: =IF($B55>Inputs!$B$11,"",D55-F55+H55+E55) -> 2.1528799e+08 | J55: =IF($B55>Inputs!$B$11,"",I55/(1+Inputs!$B$45)^A55) -> 11026068
A56: 52 | B56: =IF(Inputs!$B$9+51>Inputs!$B$11,"",Inputs!$B$9+51) -> 75 | C56: =IF($B56>Inputs!$B$11,"",IF($B56<Inputs!$B$10,"Accumulation","Retirement")) -> Retirement | D56: =IF($B56>Inputs!$B$11,"",I55) -> 2.1528799e+08 | E56: =IF($B56>Inputs!$B$11,"",IF($B56>=Inputs!$B$10,0,Retirement!$B$49*12*(1+Inputs!$B$53)^(A56-1))) -> 0 | F56: =IF($B56>Inputs!$B$11,"",IF($B56<Inputs!$B$10,0,Retirement!$B$23*(1+Inputs!$B$45)^($B56-Inputs!$B$10))) -> 13179620 | G56: =IF($B56>Inputs!$B$11,"",IF($B56<Inputs!$B$10,Inputs!$B$51,Inputs!$B$52)) -> 0.075 | H56: =IF($B56>Inputs!$B$11,"",(D56-F56)*G56) -> 15158128 | I56: =IF($B56>Inputs!$B$11,"",D56-F56+H56+E56) -> 2.172665e+08 | J56: =IF($B56>Inputs!$B$11,"",I56/(1+Inputs!$B$45)^A56) -> 10497546
A57: 53 | B57: =IF(Inputs!$B$9+52>Inputs!$B$11,"",Inputs!$B$9+52) -> 76 | C57: =IF($B57>Inputs!$B$11,"",IF($B57<Inputs!$B$10,"Accumulation","Retirement")) -> Retirement | D57: =IF($B57>Inputs!$B$11,"",I56) -> 2.172665e+08 | E57: =IF($B57>Inputs!$B$11,"",IF($B57>=Inputs!$B$10,0,Retirement!$B$49*12*(1+Inputs!$B$53)^(A57-1))) -> 0 | F57: =IF($B57>Inputs!$B$11,"",IF($B57<Inputs!$B$10,0,Retirement!$B$23*(1+Inputs!$B$45)^($B57-Inputs!$B$10))) -> 13970398 | G57: =IF($B57>Inputs!$B$11,"",IF($B57<Inputs!$B$10,Inputs!$B$51,Inputs!$B$52)) -> 0.075 | H57: =IF($B57>Inputs!$B$11,"",(D57-F57)*G57) -> 15247208 | I57: =IF($B57>Inputs!$B$11,"",D57-F57+H57+E57) -> 2.1854331e+08 | J57: =IF($B57>Inputs!$B$11,"",I57/(1+Inputs!$B$45)^A57) -> 9961544
A58: 54 | B58: =IF(Inputs!$B$9+53>Inputs!$B$11,"",Inputs!$B$9+53) -> 77 | C58: =IF($B58>Inputs!$B$11,"",IF($B58<Inputs!$B$10,"Accumulation","Retirement")) -> Retirement | D58: =IF($B58>Inputs!$B$11,"",I57) -> 2.1854331e+08 | E58: =IF($B58>Inputs!$B$11,"",IF($B58>=Inputs!$B$10,0,Retirement!$B$49*12*(1+Inputs!$B$53)^(A58-1))) -> 0 | F58: =IF($B58>Inputs!$B$11,"",IF($B58<Inputs!$B$10,0,Retirement!$B$23*(1+Inputs!$B$45)^($B58-Inputs!$B$10))) -> 14808621 | G58: =IF($B58>Inputs!$B$11,"",IF($B58<Inputs!$B$10,Inputs!$B$51,Inputs!$B$52)) -> 0.075 | H58: =IF($B58>Inputs!$B$11,"",(D58-F58)*G58) -> 15280102 | I58: =IF($B58>Inputs!$B$11,"",D58-F58+H58+E58) -> 2.1901479e+08 | J58: =IF($B58>Inputs!$B$11,"",I58/(1+Inputs!$B$45)^A58) -> 9417957.3
A59: 55 | B59: =IF(Inputs!$B$9+54>Inputs!$B$11,"",Inputs!$B$9+54) -> 78 | C59: =IF($B59>Inputs!$B$11,"",IF($B59<Inputs!$B$10,"Accumulation","Retirement")) -> Retirement | D59: =IF($B59>Inputs!$B$11,"",I58) -> 2.1901479e+08 | E59: =IF($B59>Inputs!$B$11,"",IF($B59>=Inputs!$B$10,0,Retirement!$B$49*12*(1+Inputs!$B$53)^(A59-1))) -> 0 | F59: =IF($B59>Inputs!$B$11,"",IF($B59<Inputs!$B$10,0,Retirement!$B$23*(1+Inputs!$B$45)^($B59-Inputs!$B$10))) -> 15697139 | G59: =IF($B59>Inputs!$B$11,"",IF($B59<Inputs!$B$10,Inputs!$B$51,Inputs!$B$52)) -> 0.075 | H59: =IF($B59>Inputs!$B$11,"",(D59-F59)*G59) -> 15248824 | I59: =IF($B59>Inputs!$B$11,"",D59-F59+H59+E59) -> 2.1856648e+08 | J59: =IF($B59>Inputs!$B$11,"",I59/(1+Inputs!$B$45)^A59) -> 8866678.4
A60: 56 | B60: =IF(Inputs!$B$9+55>Inputs!$B$11,"",Inputs!$B$9+55) -> 79 | C60: =IF($B60>Inputs!$B$11,"",IF($B60<Inputs!$B$10,"Accumulation","Retirement")) -> Retirement | D60: =IF($B60>Inputs!$B$11,"",I59) -> 2.1856648e+08 | E60: =IF($B60>Inputs!$B$11,"",IF($B60>=Inputs!$B$10,0,Retirement!$B$49*12*(1+Inputs!$B$53)^(A60-1))) -> 0 | F60: =IF($B60>Inputs!$B$11,"",IF($B60<Inputs!$B$10,0,Retirement!$B$23*(1+Inputs!$B$45)^($B60-Inputs!$B$10))) -> 16638967 | G60: =IF($B60>Inputs!$B$11,"",IF($B60<Inputs!$B$10,Inputs!$B$51,Inputs!$B$52)) -> 0.075 | H60: =IF($B60>Inputs!$B$11,"",(D60-F60)*G60) -> 15144563 | I60: =IF($B60>Inputs!$B$11,"",D60-F60+H60+E60) -> 2.1707207e+08 | J60: =IF($B60>Inputs!$B$11,"",I60/(1+Inputs!$B$45)^A60) -> 8307598.4
A61: 57 | B61: =IF(Inputs!$B$9+56>Inputs!$B$11,"",Inputs!$B$9+56) -> 80 | C61: =IF($B61>Inputs!$B$11,"",IF($B61<Inputs!$B$10,"Accumulation","Retirement")) -> Retirement | D61: =IF($B61>Inputs!$B$11,"",I60) -> 2.1707207e+08 | E61: =IF($B61>Inputs!$B$11,"",IF($B61>=Inputs!$B$10,0,Retirement!$B$49*12*(1+Inputs!$B$53)^(A61-1))) -> 0 | F61: =IF($B61>Inputs!$B$11,"",IF($B61<Inputs!$B$10,0,Retirement!$B$23*(1+Inputs!$B$45)^($B61-Inputs!$B$10))) -> 17637305 | G61: =IF($B61>Inputs!$B$11,"",IF($B61<Inputs!$B$10,Inputs!$B$51,Inputs!$B$52)) -> 0.075 | H61: =IF($B61>Inputs!$B$11,"",(D61-F61)*G61) -> 14957607 | I61: =IF($B61>Inputs!$B$11,"",D61-F61+H61+E61) -> 2.1439237e+08 | J61: =IF($B61>Inputs!$B$11,"",I61/(1+Inputs!$B$45)^A61) -> 7740606.9
A62: 58 | B62: =IF(Inputs!$B$9+57>Inputs!$B$11,"",Inputs!$B$9+57) -> 81 | C62: =IF($B62>Inputs!$B$11,"",IF($B62<Inputs!$B$10,"Accumulation","Retirement")) -> Retirement | D62: =IF($B62>Inputs!$B$11,"",I61) -> 2.1439237e+08 | E62: =IF($B62>Inputs!$B$11,"",IF($B62>=Inputs!$B$10,0,Retirement!$B$49*12*(1+Inputs!$B$53)^(A62-1))) -> 0 | F62: =IF($B62>Inputs!$B$11,"",IF($B62<Inputs!$B$10,0,Retirement!$B$23*(1+Inputs!$B$45)^($B62-Inputs!$B$10))) -> 18695543 | G62: =IF($B62>Inputs!$B$11,"",IF($B62<Inputs!$B$10,Inputs!$B$51,Inputs!$B$52)) -> 0.075 | H62: =IF($B62>Inputs!$B$11,"",(D62-F62)*G62) -> 14677262 | I62: =IF($B62>Inputs!$B$11,"",D62-F62+H62+E62) -> 2.1037409e+08 | J62: =IF($B62>Inputs!$B$11,"",I62/(1+Inputs!$B$45)^A62) -> 7165591.9
A63: 59 | B63: =IF(Inputs!$B$9+58>Inputs!$B$11,"",Inputs!$B$9+58) -> 82 | C63: =IF($B63>Inputs!$B$11,"",IF($B63<Inputs!$B$10,"Accumulation","Retirement")) -> Retirement | D63: =IF($B63>Inputs!$B$11,"",I62) -> 2.1037409e+08 | E63: =IF($B63>Inputs!$B$11,"",IF($B63>=Inputs!$B$10,0,Retirement!$B$49*12*(1+Inputs!$B$53)^(A63-1))) -> 0 | F63: =IF($B63>Inputs!$B$11,"",IF($B63<Inputs!$B$10,0,Retirement!$B$23*(1+Inputs!$B$45)^($B63-Inputs!$B$10))) -> 19817276 | G63: =IF($B63>Inputs!$B$11,"",IF($B63<Inputs!$B$10,Inputs!$B$51,Inputs!$B$52)) -> 0.075 | H63: =IF($B63>Inputs!$B$11,"",(D63-F63)*G63) -> 14291761 | I63: =IF($B63>Inputs!$B$11,"",D63-F63+H63+E63) -> 2.0484858e+08 | J63: =IF($B63>Inputs!$B$11,"",I63/(1+Inputs!$B$45)^A63) -> 6582439.9
A64: 60 | B64: =IF(Inputs!$B$9+59>Inputs!$B$11,"",Inputs!$B$9+59) -> 83 | C64: =IF($B64>Inputs!$B$11,"",IF($B64<Inputs!$B$10,"Accumulation","Retirement")) -> Retirement | D64: =IF($B64>Inputs!$B$11,"",I63) -> 2.0484858e+08 | E64: =IF($B64>Inputs!$B$11,"",IF($B64>=Inputs!$B$10,0,Retirement!$B$49*12*(1+Inputs!$B$53)^(A64-1))) -> 0 | F64: =IF($B64>Inputs!$B$11,"",IF($B64<Inputs!$B$10,0,Retirement!$B$23*(1+Inputs!$B$45)^($B64-Inputs!$B$10))) -> 21006313 | G64: =IF($B64>Inputs!$B$11,"",IF($B64<Inputs!$B$10,Inputs!$B$51,Inputs!$B$52)) -> 0.075 | H64: =IF($B64>Inputs!$B$11,"",(D64-F64)*G64) -> 13788170 | I64: =IF($B64>Inputs!$B$11,"",D64-F64+H64+E64) -> 1.9763043e+08 | J64: =IF($B64>Inputs!$B$11,"",I64/(1+Inputs!$B$45)^A64) -> 5991035.7
A65: 61 | B65: =IF(Inputs!$B$9+60>Inputs!$B$11,"",Inputs!$B$9+60) -> 84 | C65: =IF($B65>Inputs!$B$11,"",IF($B65<Inputs!$B$10,"Accumulation","Retirement")) -> Retirement | D65: =IF($B65>Inputs!$B$11,"",I64) -> 1.9763043e+08 | E65: =IF($B65>Inputs!$B$11,"",IF($B65>=Inputs!$B$10,0,Retirement!$B$49*12*(1+Inputs!$B$53)^(A65-1))) -> 0 | F65: =IF($B65>Inputs!$B$11,"",IF($B65<Inputs!$B$10,0,Retirement!$B$23*(1+Inputs!$B$45)^($B65-Inputs!$B$10))) -> 22266691 | G65: =IF($B65>Inputs!$B$11,"",IF($B65<Inputs!$B$10,Inputs!$B$51,Inputs!$B$52)) -> 0.075 | H65: =IF($B65>Inputs!$B$11,"",(D65-F65)*G65) -> 13152281 | I65: =IF($B65>Inputs!$B$11,"",D65-F65+H65+E65) -> 1.8851602e+08 | J65: =IF($B65>Inputs!$B$11,"",I65/(1+Inputs!$B$45)^A65) -> 5391262.7
A66: 62 | B66: =IF(Inputs!$B$9+61>Inputs!$B$11,"",Inputs!$B$9+61) -> 85 | C66: =IF($B66>Inputs!$B$11,"",IF($B66<Inputs!$B$10,"Accumulation","Retirement")) -> Retirement | D66: =IF($B66>Inputs!$B$11,"",I65) -> 1.8851602e+08 | E66: =IF($B66>Inputs!$B$11,"",IF($B66>=Inputs!$B$10,0,Retirement!$B$49*12*(1+Inputs!$B$53)^(A66-1))) -> 0 | F66: =IF($B66>Inputs!$B$11,"",IF($B66<Inputs!$B$10,0,Retirement!$B$23*(1+Inputs!$B$45)^($B66-Inputs!$B$10))) -> 23602693 | G66: =IF($B66>Inputs!$B$11,"",IF($B66<Inputs!$B$10,Inputs!$B$51,Inputs!$B$52)) -> 0.075 | H66: =IF($B66>Inputs!$B$11,"",(D66-F66)*G66) -> 12368500 | I66: =IF($B66>Inputs!$B$11,"",D66-F66+H66+E66) -> 1.7728183e+08 | J66: =IF($B66>Inputs!$B$11,"",I66/(1+Inputs!$B$45)^A66) -> 4783002.2
A67: 63 | B67: =IF(Inputs!$B$9+62>Inputs!$B$11,"",Inputs!$B$9+62) | C67: =IF($B67>Inputs!$B$11,"",IF($B67<Inputs!$B$10,"Accumulation","Retirement")) | D67: =IF($B67>Inputs!$B$11,"",I66) | E67: =IF($B67>Inputs!$B$11,"",IF($B67>=Inputs!$B$10,0,Retirement!$B$49*12*(1+Inputs!$B$53)^(A67-1))) | F67: =IF($B67>Inputs!$B$11,"",IF($B67<Inputs!$B$10,0,Retirement!$B$23*(1+Inputs!$B$45)^($B67-Inputs!$B$10))) | G67: =IF($B67>Inputs!$B$11,"",IF($B67<Inputs!$B$10,Inputs!$B$51,Inputs!$B$52)) | H67: =IF($B67>Inputs!$B$11,"",(D67-F67)*G67) | I67: =IF($B67>Inputs!$B$11,"",D67-F67+H67+E67) | J67: =IF($B67>Inputs!$B$11,"",I67/(1+Inputs!$B$45)^A67)
A68: 64 | B68: =IF(Inputs!$B$9+63>Inputs!$B$11,"",Inputs!$B$9+63) | C68: =IF($B68>Inputs!$B$11,"",IF($B68<Inputs!$B$10,"Accumulation","Retirement")) | D68: =IF($B68>Inputs!$B$11,"",I67) | E68: =IF($B68>Inputs!$B$11,"",IF($B68>=Inputs!$B$10,0,Retirement!$B$49*12*(1+Inputs!$B$53)^(A68-1))) | F68: =IF($B68>Inputs!$B$11,"",IF($B68<Inputs!$B$10,0,Retirement!$B$23*(1+Inputs!$B$45)^($B68-Inputs!$B$10))) | G68: =IF($B68>Inputs!$B$11,"",IF($B68<Inputs!$B$10,Inputs!$B$51,Inputs!$B$52)) | H68: =IF($B68>Inputs!$B$11,"",(D68-F68)*G68) | I68: =IF($B68>Inputs!$B$11,"",D68-F68+H68+E68) | J68: =IF($B68>Inputs!$B$11,"",I68/(1+Inputs!$B$45)^A68)
A69: 65 | B69: =IF(Inputs!$B$9+64>Inputs!$B$11,"",Inputs!$B$9+64) | C69: =IF($B69>Inputs!$B$11,"",IF($B69<Inputs!$B$10,"Accumulation","Retirement")) | D69: =IF($B69>Inputs!$B$11,"",I68) | E69: =IF($B69>Inputs!$B$11,"",IF($B69>=Inputs!$B$10,0,Retirement!$B$49*12*(1+Inputs!$B$53)^(A69-1))) | F69: =IF($B69>Inputs!$B$11,"",IF($B69<Inputs!$B$10,0,Retirement!$B$23*(1+Inputs!$B$45)^($B69-Inputs!$B$10))) | G69: =IF($B69>Inputs!$B$11,"",IF($B69<Inputs!$B$10,Inputs!$B$51,Inputs!$B$52)) | H69: =IF($B69>Inputs!$B$11,"",(D69-F69)*G69) | I69: =IF($B69>Inputs!$B$11,"",D69-F69+H69+E69) | J69: =IF($B69>Inputs!$B$11,"",I69/(1+Inputs!$B$45)^A69)
A70: 66 | B70: =IF(Inputs!$B$9+65>Inputs!$B$11,"",Inputs!$B$9+65) | C70: =IF($B70>Inputs!$B$11,"",IF($B70<Inputs!$B$10,"Accumulation","Retirement")) | D70: =IF($B70>Inputs!$B$11,"",I69) | E70: =IF($B70>Inputs!$B$11,"",IF($B70>=Inputs!$B$10,0,Retirement!$B$49*12*(1+Inputs!$B$53)^(A70-1))) | F70: =IF($B70>Inputs!$B$11,"",IF($B70<Inputs!$B$10,0,Retirement!$B$23*(1+Inputs!$B$45)^($B70-Inputs!$B$10))) | G70: =IF($B70>Inputs!$B$11,"",IF($B70<Inputs!$B$10,Inputs!$B$51,Inputs!$B$52)) | H70: =IF($B70>Inputs!$B$11,"",(D70-F70)*G70) | I70: =IF($B70>Inputs!$B$11,"",D70-F70+H70+E70) | J70: =IF($B70>Inputs!$B$11,"",I70/(1+Inputs!$B$45)^A70)
A71: 67 | B71: =IF(Inputs!$B$9+66>Inputs!$B$11,"",Inputs!$B$9+66) | C71: =IF($B71>Inputs!$B$11,"",IF($B71<Inputs!$B$10,"Accumulation","Retirement")) | D71: =IF($B71>Inputs!$B$11,"",I70) | E71: =IF($B71>Inputs!$B$11,"",IF($B71>=Inputs!$B$10,0,Retirement!$B$49*12*(1+Inputs!$B$53)^(A71-1))) | F71: =IF($B71>Inputs!$B$11,"",IF($B71<Inputs!$B$10,0,Retirement!$B$23*(1+Inputs!$B$45)^($B71-Inputs!$B$10))) | G71: =IF($B71>Inputs!$B$11,"",IF($B71<Inputs!$B$10,Inputs!$B$51,Inputs!$B$52)) | H71: =IF($B71>Inputs!$B$11,"",(D71-F71)*G71) | I71: =IF($B71>Inputs!$B$11,"",D71-F71+H71+E71) | J71: =IF($B71>Inputs!$B$11,"",I71/(1+Inputs!$B$45)^A71)
A72: 68 | B72: =IF(Inputs!$B$9+67>Inputs!$B$11,"",Inputs!$B$9+67) | C72: =IF($B72>Inputs!$B$11,"",IF($B72<Inputs!$B$10,"Accumulation","Retirement")) | D72: =IF($B72>Inputs!$B$11,"",I71) | E72: =IF($B72>Inputs!$B$11,"",IF($B72>=Inputs!$B$10,0,Retirement!$B$49*12*(1+Inputs!$B$53)^(A72-1))) | F72: =IF($B72>Inputs!$B$11,"",IF($B72<Inputs!$B$10,0,Retirement!$B$23*(1+Inputs!$B$45)^($B72-Inputs!$B$10))) | G72: =IF($B72>Inputs!$B$11,"",IF($B72<Inputs!$B$10,Inputs!$B$51,Inputs!$B$52)) | H72: =IF($B72>Inputs!$B$11,"",(D72-F72)*G72) | I72: =IF($B72>Inputs!$B$11,"",D72-F72+H72+E72) | J72: =IF($B72>Inputs!$B$11,"",I72/(1+Inputs!$B$45)^A72)
A73: 69 | B73: =IF(Inputs!$B$9+68>Inputs!$B$11,"",Inputs!$B$9+68) | C73: =IF($B73>Inputs!$B$11,"",IF($B73<Inputs!$B$10,"Accumulation","Retirement")) | D73: =IF($B73>Inputs!$B$11,"",I72) | E73: =IF($B73>Inputs!$B$11,"",IF($B73>=Inputs!$B$10,0,Retirement!$B$49*12*(1+Inputs!$B$53)^(A73-1))) | F73: =IF($B73>Inputs!$B$11,"",IF($B73<Inputs!$B$10,0,Retirement!$B$23*(1+Inputs!$B$45)^($B73-Inputs!$B$10))) | G73: =IF($B73>Inputs!$B$11,"",IF($B73<Inputs!$B$10,Inputs!$B$51,Inputs!$B$52)) | H73: =IF($B73>Inputs!$B$11,"",(D73-F73)*G73) | I73: =IF($B73>Inputs!$B$11,"",D73-F73+H73+E73) | J73: =IF($B73>Inputs!$B$11,"",I73/(1+Inputs!$B$45)^A73)
A74: 70 | B74: =IF(Inputs!$B$9+69>Inputs!$B$11,"",Inputs!$B$9+69) | C74: =IF($B74>Inputs!$B$11,"",IF($B74<Inputs!$B$10,"Accumulation","Retirement")) | D74: =IF($B74>Inputs!$B$11,"",I73) | E74: =IF($B74>Inputs!$B$11,"",IF($B74>=Inputs!$B$10,0,Retirement!$B$49*12*(1+Inputs!$B$53)^(A74-1))) | F74: =IF($B74>Inputs!$B$11,"",IF($B74<Inputs!$B$10,0,Retirement!$B$23*(1+Inputs!$B$45)^($B74-Inputs!$B$10))) | G74: =IF($B74>Inputs!$B$11,"",IF($B74<Inputs!$B$10,Inputs!$B$51,Inputs!$B$52)) | H74: =IF($B74>Inputs!$B$11,"",(D74-F74)*G74) | I74: =IF($B74>Inputs!$B$11,"",D74-F74+H74+E74) | J74: =IF($B74>Inputs!$B$11,"",I74/(1+Inputs!$B$45)^A74)
A75: 71 | B75: =IF(Inputs!$B$9+70>Inputs!$B$11,"",Inputs!$B$9+70) | C75: =IF($B75>Inputs!$B$11,"",IF($B75<Inputs!$B$10,"Accumulation","Retirement")) | D75: =IF($B75>Inputs!$B$11,"",I74) | E75: =IF($B75>Inputs!$B$11,"",IF($B75>=Inputs!$B$10,0,Retirement!$B$49*12*(1+Inputs!$B$53)^(A75-1))) | F75: =IF($B75>Inputs!$B$11,"",IF($B75<Inputs!$B$10,0,Retirement!$B$23*(1+Inputs!$B$45)^($B75-Inputs!$B$10))) | G75: =IF($B75>Inputs!$B$11,"",IF($B75<Inputs!$B$10,Inputs!$B$51,Inputs!$B$52)) | H75: =IF($B75>Inputs!$B$11,"",(D75-F75)*G75) | I75: =IF($B75>Inputs!$B$11,"",D75-F75+H75+E75) | J75: =IF($B75>Inputs!$B$11,"",I75/(1+Inputs!$B$45)^A75)
A76: 72 | B76: =IF(Inputs!$B$9+71>Inputs!$B$11,"",Inputs!$B$9+71) | C76: =IF($B76>Inputs!$B$11,"",IF($B76<Inputs!$B$10,"Accumulation","Retirement")) | D76: =IF($B76>Inputs!$B$11,"",I75) | E76: =IF($B76>Inputs!$B$11,"",IF($B76>=Inputs!$B$10,0,Retirement!$B$49*12*(1+Inputs!$B$53)^(A76-1))) | F76: =IF($B76>Inputs!$B$11,"",IF($B76<Inputs!$B$10,0,Retirement!$B$23*(1+Inputs!$B$45)^($B76-Inputs!$B$10))) | G76: =IF($B76>Inputs!$B$11,"",IF($B76<Inputs!$B$10,Inputs!$B$51,Inputs!$B$52)) | H76: =IF($B76>Inputs!$B$11,"",(D76-F76)*G76) | I76: =IF($B76>Inputs!$B$11,"",D76-F76+H76+E76) | J76: =IF($B76>Inputs!$B$11,"",I76/(1+Inputs!$B$45)^A76)
A78: COLUMN LOGIC
A79: Opening Corpus | B79: Year 1 = existing equity + debt investments (the cash and FD balance is excluded because it is the emergency fund, not retirement money). Every later year = the previous year's Closing Corpus.
A80: Annual Investment | B80: Formula: Year-1 Step-Up SIP x 12 x (1 + Step-Up Rate) ^ (Year - 1). Zero once age reaches the retirement age.
A81: Annual Withdrawal | B81: Formula: First-Year Retirement Expense x (1 + Inflation) ^ (Age - Retirement Age). Zero before retirement. Withdrawals grow every year, which is the whole point.
A82: Return Rate | B82: Formula: Blended Pre-Retirement Return before retirement, Post-Retirement Return afterwards. Risk comes down when the salary stops.
A83: Growth | B83: Formula: (Opening - Withdrawal) x Return Rate. Withdrawals are taken at the START of the year so they earn nothing, and the year's investment is credited at the END so it earns nothing either. This is the same timing convention the Retirement sheet solves under, which is why the two sheets agree.
A84: Closing Corpus | B84: Formula: Opening - Withdrawal + Growth + Investment.
A85: Closing in Today's Money | B85: Formula: Closing Corpus / (1 + Inflation) ^ Year. Strips inflation out so the numbers stay intuitive.

Sheet Calculators
A1: 6. STANDALONE CALCULATORS - USE FOR ANY CLIENT, ANY SCENARIO
A3: These blocks are INDEPENDENT of the rest of the workbook. Type into the yellow cells and read the answer. Nothing here feeds the plan, so experiment freely.
A5: CALC 1 - SIP FUTURE VALUE (what will my monthly SIP become?)
A6: Parameter | B6: Value | C6: Unit | D6: Formula / Logic Used
A7: Monthly SIP Amount | B7: 25000 | C7: ₹ p.m. | D7: Your input.
A8: Expected Annual Return | B8: 0.12 | C8: % | D8: Your input.
A9: Investment Period | B9: 20 | C9: years | D9: Your input.
A10: Future Value | B10: =FV(B8/12,B9*12,-B7) -> 24731384 | C10: ₹ | D10: Formula: FV(Annual Return / 12, Years x 12, -Monthly SIP). Rate and period are both converted to MONTHS because the instalment is monthly. The SIP is negative because it is cash leaving your pocket.
A11: Total Amount Invested | B11: =B7*B9*12 -> 6000000 | C11: ₹ | D11: Formula: Monthly SIP x Years x 12
A12: Wealth Gained | B12: =B10-B11 -> 18731384 | C12: ₹ | D12: Formula: Future Value - Total Invested
A13: Gain Multiple | B13: =IFERROR(B10/B11,0) -> 4.1218974 | C13: x | D13: Formula: Future Value / Total Invested
A15: CALC 2 - STEP-UP SIP FUTURE VALUE (SIP increased every year)
A16: Parameter | B16: Value | C16: Unit | D16: Formula / Logic Used
A17: Year-1 Monthly SIP | B17: 20000 | C17: ₹ p.m. | D17: Your input.
A18: Annual Step-Up Rate | B18: 0.1 | C18: % | D18: How much you raise the SIP each year.
A19: Expected Annual Return | B19: 0.12 | C19: % | D19: Your input.
A20: Investment Period | B20: 20 | C20: years | D20: Your input.
A21: Future Value | B21: =IF(ABS(B19-B18)<0.0001,B17*12*B20*(1+B19)^(B20-1),B17*12*((1+B19)^B20-(1+B18)^B20)/(B19-B18)) -> 35025518 | C21: ₹ | D21: Formula: A x [ (1+r)^n - (1+g)^n ] / (r - g), where A = year-1 ANNUAL investment, r = return, g = step-up rate, n = years. Future value of a growing annuity. The IF handles the r = g case, where the formula would divide by zero.
A22: Total Amount Invested | B22: =IF(ABS(B18)<0.0001,B17*12*B20,B17*12*((1+B18)^B20-1)/B18) -> 13746000 | C22: ₹ | D22: Formula: A x [ (1+g)^n - 1 ] / g. Sum of a geometric series - the contributions themselves, before any return.
A23: Wealth Gained | B23: =B21-B22 -> 21279518 | C23: ₹ | D23: Formula: Future Value - Total Invested
A25: CALC 3 - LUMPSUM FUTURE VALUE
A26: Parameter | B26: Value | C26: Unit | D26: Formula / Logic Used
A27: Lumpsum Invested Today | B27: 1000000 | C27: ₹ | D27: Your input.
A28: Expected Annual Return | B28: 0.12 | C28: % | D28: Your input.
A29: Investment Period | B29: 20 | C29: years | D29: Your input.
A30: Future Value | B30: =FV(B28,B29,0,-B27) -> 9646293.1 | C30: ₹ | D30: Formula: FV(Return, Years, 0, -Lumpsum). Equivalent to Lumpsum x (1 + Return) ^ Years. The 0 is the payment argument: there are no recurring instalments.
A31: Wealth Gained | B31: =B30-B27 -> 8646293.1 | C31: ₹ | D31: Formula: Future Value - Amount Invested
A33: CALC 4 - SIP NEEDED FOR A TARGET (goal-based, reverse SIP)
A34: Parameter | B34: Value | C34: Unit | D34: Formula / Logic Used
A35: Target Amount (future value needed) | B35: 10000000 | C35: ₹ | D35: Your input.
A36: Expected Annual Return | B36: 0.12 | C36: % | D36: Your input.
A37: Time Available | B37: 15 | C37: years | D37: Your input.
A38: Monthly SIP Required | B38: =-PMT(B36/12,B37*12,0,B35) -> 20016.806 | C38: ₹ p.m. | D38: Formula: -PMT(Return / 12, Years x 12, 0, Target). PMT solves for the instalment that turns a present value of 0 into the target. The leading minus flips the sign from outflow to a readable positive.
A39: Lumpsum Required Instead | B39: =B35/(1+B36)^B37 -> 1826962.6 | C39: ₹ | D39: Formula: Target / (1 + Return) ^ Years. Present value of the target - one payment today instead of many.
A41: CALC 5 - INFLATION IMPACT (future cost & present value)
A42: Parameter | B42: Value | C42: Unit | D42: Formula / Logic Used
A43: Cost Today | B43: 100000 | C43: ₹ | D43: Your input.
A44: Inflation Rate | B44: 0.06 | C44: % | D44: Your input. Use 10% for medical, 8% for education.
A45: Number of Years | B45: 25 | C45: years | D45: Your input.
A46: Cost After N Years | B46: =FV(B44,B45,0,-B43) -> 429187.07 | C46: ₹ | D46: Formula: FV(Inflation, Years, 0, -Cost Today). What the same basket will cost later.
A47: Today's Value of that Future Amount | B47: =B46/(1+B44)^B45 -> 100000 | C47: ₹ | D47: Formula: Future Amount / (1 + Inflation) ^ Years. Deflating back - this should return the Cost Today, which is the check that the two directions agree.
A48: Purchasing Power Lost | B48: =1-1/(1+B44)^B45 -> 0.76700137 | C48: % | D48: Formula: 1 - 1 / (1 + Inflation) ^ Years. The share of a rupee's buying power destroyed over the period.
A50: CALC 6 - SWP / HOW LONG WILL A CORPUS LAST?
A51: Parameter | B51: Value | C51: Unit | D51: Formula / Logic Used
A52: Corpus Available | B52: 50000000 | C52: ₹ | D52: Your input.
A53: Monthly Withdrawal | B53: 200000 | C53: ₹ p.m. | D53: Your input.
A54: Expected Annual Return on Corpus | B54: 0.075 | C54: % | D54: Your input.
A55: Months the Corpus Lasts | B55: =IFERROR(NPER(B54/12,B53,-B52),999) -> 999 | C55: months | D55: Formula: NPER(Return / 12, Monthly Withdrawal, -Corpus). NPER solves for the number of periods until the balance hits zero. If the withdrawal is smaller than the return earned, the corpus never depletes and this shows 999.
A56: Years the Corpus Lasts | B56: =B55/12 -> 83.25 | C56: years | D56: Formula: Months / 12
A57: Withdrawal Rate | B57: =IFERROR(B53*12/B52,0) -> 0.048 | C57: % | D57: Formula: Annual Withdrawal / Corpus. Keep this at or under 4% for a 25-year retirement; 3-3.5% if the retirement could run 30+ years.
A59: CALC 7 - LOAN EMI
A60: Parameter | B60: Value | C60: Unit | D60: Formula / Logic Used
A61: Loan Amount | B61: 5000000 | C61: ₹ | D61: Your input.
A62: Annual Interest Rate | B62: 0.085 | C62: % | D62: Your input.
A63: Tenure | B63: 20 | C63: years | D63: Your input.
A64: Monthly EMI | B64: =-PMT(B62/12,B63*12,B61) -> 43391.162 | C64: ₹ p.m. | D64: Formula: -PMT(Rate / 12, Years x 12, Loan Amount). Here the loan is the PRESENT value (money received), so PMT returns the repayment.
A65: Total Amount Repaid | B65: =B64*B63*12 -> 10413879 | C65: ₹ | D65: Formula: EMI x Years x 12
A66: Total Interest Paid | B66: =B65-B61 -> 5413878.8 | C66: ₹ | D66: Formula: Total Repaid - Loan Amount
A67: Interest as % of Loan | B67: =IFERROR(B66/B61,0) -> 1.0827758 | C67: % | D67: Formula: Total Interest / Loan Amount
A69: CALC 8 - TIME & RATE SOLVERS
A70: Parameter | B70: Value | C70: Unit | D70: Formula / Logic Used
A71: Target Amount | B71: 10000000 | C71: ₹ | D71: Your input.
A72: Monthly SIP You Can Afford | B72: 25000 | C72: ₹ p.m. | D72: Your input.
A73: Expected Annual Return | B73: 0.12 | C73: % | D73: Your input.
A74: Years Needed to Reach the Target | B74: =IFERROR(NPER(B73/12,-B72,0,B71)/12,0) -> 13.478931 | C74: years | D74: Formula: NPER(Return / 12, -Monthly SIP, 0, Target) / 12. Solves for TIME instead of amount.
A75: Years You Actually Have | B75: 10 | C75: years | D75: Your input.
A76: Return Required to Hit the Target in that Time | B76: =IFERROR(RATE(B75*12,-B72,0,B71)*12,0) -> 0.20957668 | C76: % | D76: Formula: RATE(Years x 12, -Monthly SIP, 0, Target) x 12. Solves for the RETURN. If this comes out above ~13-14%, the goal is not realistic - change the amount, the SIP or the timeline rather than the assumption.
A77: Real (Inflation-Adjusted) Return | B77: =(1+B73)/(1+0.06)-1 -> 0.056603774 | C77: % | D77: Formula: (1 + Nominal Return) / (1 + 6% Inflation) - 1. Fisher equation. Edit the 0.06 for a different inflation rate.
A78: Years for Money to Double | B78: =IFERROR(LOG(2)/LOG(1+B73),0) -> 6.1162554 | C78: years | D78: Formula: LOG(2) / LOG(1 + Return). The exact version of the Rule of 72.
A80: SIGN CONVENTION: Excel's financial functions treat money leaving you as NEGATIVE and money coming to you as POSITIVE. That is why SIPs and lumpsums are entered with a minus sign inside FV, and why PMT results are negated to display as positive. Get the signs wrong and the answer is right in magnitude but backwards in sign.

Sheet Allocation
A1: 7. ASSET ALLOCATION - CURRENT SPLIT & GLIDE PATH TO RETIREMENT
A4: A. RECOMMENDED ALLOCATION AT THE CLIENT'S CURRENT AGE
A5: Parameter | B5: Value | C5: Unit | D5: Formula / Logic Used
A6: Current Age | B6: =Inputs!B9 -> 24 | C6: years | D6: Link to Inputs.
A7: Equity Allocation | B7: =INDEX(Tables!$B$16:$B$23,MATCH(B6,Tables!$A$16:$A$23,1)) -> 0.75 | C7: % | D7: Formula: INDEX(equity weights, MATCH(Age, age bands, 1)). Glide path lookup on the Tables sheet.
A8: Debt Allocation | B8: =INDEX(Tables!$C$16:$C$23,MATCH(B6,Tables!$A$16:$A$23,1)) -> 0.15 | C8: % | D8: Formula: INDEX(debt weights, MATCH(Age, age bands, 1))
A9: Gold / Commodity Allocation | B9: =INDEX(Tables!$D$16:$D$23,MATCH(B6,Tables!$A$16:$A$23,1)) -> 0.1 | C9: % | D9: Formula: INDEX(gold weights, MATCH(Age, age bands, 1))
A10: Total | B10: =B7+B8+B9 -> 1 | C10: % | D10: Must equal 100%.
A12: B. HOW TO SPLIT THE MONTHLY INVESTIBLE SURPLUS
A13: Parameter | B13: Value | C13: Unit | D13: Formula / Logic Used
A14: Monthly Investible Surplus | B14: =Inputs!B26 -> 128558.33 | C14: ₹ p.m. | D14: Link to Inputs.
A15: Into Equity (index + flexicap + midcap SIPs) | B15: =B14*B7 -> 96418.75 | C15: ₹ p.m. | D15: Formula: Monthly Surplus x Equity Weight
A16: Into Debt (EPF / PPF / short-duration & corporate bond funds) | B16: =B14*B8 -> 19283.75 | C16: ₹ p.m. | D16: Formula: Monthly Surplus x Debt Weight
A17: Into Gold (sovereign gold / gold ETF) | B17: =B14*B9 -> 12855.833 | C17: ₹ p.m. | D17: Formula: Monthly Surplus x Gold Weight
A18: Total Allocated | B18: =SUM(B15:B17) -> 128558.33 | C18: ₹ p.m. | D18: Formula: Equity + Debt + Gold. Should equal the Monthly Investible Surplus.
A20: SEQUENCING RULE: until the emergency fund on the Goals sheet is fully built, route 100% of the surplus into liquid funds and sweep-in FDs regardless of the split above. Allocation matters only once the safety net exists.
A22: C. GLIDE PATH - HOW THE MIX SHOULD SHIFT WITH AGE
A23: Age | B23: Equity % | C23: Debt % | D23: Gold %
A24: 25 | B24: =INDEX(Tables!$B$16:$B$23,MATCH(A24,Tables!$A$16:$A$23,1)) -> 0.75 | C24: =INDEX(Tables!$C$16:$C$23,MATCH(A24,Tables!$A$16:$A$23,1)) -> 0.15 | D24: =INDEX(Tables!$D$16:$D$23,MATCH(A24,Tables!$A$16:$A$23,1)) -> 0.1
A25: 30 | B25: =INDEX(Tables!$B$16:$B$23,MATCH(A25,Tables!$A$16:$A$23,1)) -> 0.75 | C25: =INDEX(Tables!$C$16:$C$23,MATCH(A25,Tables!$A$16:$A$23,1)) -> 0.15 | D25: =INDEX(Tables!$D$16:$D$23,MATCH(A25,Tables!$A$16:$A$23,1)) -> 0.1
A26: 35 | B26: =INDEX(Tables!$B$16:$B$23,MATCH(A26,Tables!$A$16:$A$23,1)) -> 0.7 | C26: =INDEX(Tables!$C$16:$C$23,MATCH(A26,Tables!$A$16:$A$23,1)) -> 0.2 | D26: =INDEX(Tables!$D$16:$D$23,MATCH(A26,Tables!$A$16:$A$23,1)) -> 0.1
A27: 40 | B27: =INDEX(Tables!$B$16:$B$23,MATCH(A27,Tables!$A$16:$A$23,1)) -> 0.65 | C27: =INDEX(Tables!$C$16:$C$23,MATCH(A27,Tables!$A$16:$A$23,1)) -> 0.25 | D27: =INDEX(Tables!$D$16:$D$23,MATCH(A27,Tables!$A$16:$A$23,1)) -> 0.1
A28: 45 | B28: =INDEX(Tables!$B$16:$B$23,MATCH(A28,Tables!$A$16:$A$23,1)) -> 0.6 | C28: =INDEX(Tables!$C$16:$C$23,MATCH(A28,Tables!$A$16:$A$23,1)) -> 0.3 | D28: =INDEX(Tables!$D$16:$D$23,MATCH(A28,Tables!$A$16:$A$23,1)) -> 0.1
A29: 50 | B29: =INDEX(Tables!$B$16:$B$23,MATCH(A29,Tables!$A$16:$A$23,1)) -> 0.5 | C29: =INDEX(Tables!$C$16:$C$23,MATCH(A29,Tables!$A$16:$A$23,1)) -> 0.4 | D29: =INDEX(Tables!$D$16:$D$23,MATCH(A29,Tables!$A$16:$A$23,1)) -> 0.1
A30: 55 | B30: =INDEX(Tables!$B$16:$B$23,MATCH(A30,Tables!$A$16:$A$23,1)) -> 0.4 | C30: =INDEX(Tables!$C$16:$C$23,MATCH(A30,Tables!$A$16:$A$23,1)) -> 0.5 | D30: =INDEX(Tables!$D$16:$D$23,MATCH(A30,Tables!$A$16:$A$23,1)) -> 0.1
A31: 60 | B31: =INDEX(Tables!$B$16:$B$23,MATCH(A31,Tables!$A$16:$A$23,1)) -> 0.3 | C31: =INDEX(Tables!$C$16:$C$23,MATCH(A31,Tables!$A$16:$A$23,1)) -> 0.6 | D31: =INDEX(Tables!$D$16:$D$23,MATCH(A31,Tables!$A$16:$A$23,1)) -> 0.1
A32: 65 | B32: =INDEX(Tables!$B$16:$B$23,MATCH(A32,Tables!$A$16:$A$23,1)) -> 0.25 | C32: =INDEX(Tables!$C$16:$C$23,MATCH(A32,Tables!$A$16:$A$23,1)) -> 0.65 | D32: =INDEX(Tables!$D$16:$D$23,MATCH(A32,Tables!$A$16:$A$23,1)) -> 0.1
A33: 70 | B33: =INDEX(Tables!$B$16:$B$23,MATCH(A33,Tables!$A$16:$A$23,1)) -> 0.25 | C33: =INDEX(Tables!$C$16:$C$23,MATCH(A33,Tables!$A$16:$A$23,1)) -> 0.65 | D33: =INDEX(Tables!$D$16:$D$23,MATCH(A33,Tables!$A$16:$A$23,1)) -> 0.1
A34: 75 | B34: =INDEX(Tables!$B$16:$B$23,MATCH(A34,Tables!$A$16:$A$23,1)) -> 0.25 | C34: =INDEX(Tables!$C$16:$C$23,MATCH(A34,Tables!$A$16:$A$23,1)) -> 0.65 | D34: =INDEX(Tables!$D$16:$D$23,MATCH(A34,Tables!$A$16:$A$23,1)) -> 0.1
A35: 80 | B35: =INDEX(Tables!$B$16:$B$23,MATCH(A35,Tables!$A$16:$A$23,1)) -> 0.25 | C35: =INDEX(Tables!$C$16:$C$23,MATCH(A35,Tables!$A$16:$A$23,1)) -> 0.65 | D35: =INDEX(Tables!$D$16:$D$23,MATCH(A35,Tables!$A$16:$A$23,1)) -> 0.1
A36: 85 | B36: =INDEX(Tables!$B$16:$B$23,MATCH(A36,Tables!$A$16:$A$23,1)) -> 0.25 | C36: =INDEX(Tables!$C$16:$C$23,MATCH(A36,Tables!$A$16:$A$23,1)) -> 0.65 | D36: =INDEX(Tables!$D$16:$D$23,MATCH(A36,Tables!$A$16:$A$23,1)) -> 0.1
A38: REBALANCING: check the actual portfolio against these weights once a year and after any move above 10 percentage points. Rebalancing is what mechanically enforces selling high and buying low; drift is what quietly turns a 75/25 portfolio into a 90/10 one right before it matters.

Sheet FormulaGuide
A1: 8. FORMULA GUIDE - EVERY FUNCTION AND CONCEPT USED IN THIS WORKBOOK
A3: PART 1 - EXCEL FUNCTIONS
A4: Function | B4: Syntax | C4: What It Does (plain English) | D4: Used On
A5: FV | B5: FV(rate, nper, pmt, [pv], [type]) | C5: Future Value. Grows money forward. Give it a rate per period, a number of periods, and either a recurring payment (pmt) or a starting lump (pv) - entered NEGATIVE because it is cash you part with. Returns what it becomes. | D5: Goals, Retirement, Insurance, Calculators
A6: PV | B6: PV(rate, nper, pmt, [fv], [type]) | C6: Present Value. The mirror of FV - discounts a future stream back to what it is worth today. type = 1 makes it an annuity-due (cash at the START of each period), which is how retirement withdrawals and family expenses actually behave. | D6: Insurance (HLV), Retirement (corpus)
A7: PMT | B7: PMT(rate, nper, pv, [fv], [type]) | C7: Payment. Solves for the level instalment. With pv = 0 and fv = target it gives the SIP needed to build a corpus; with pv = loan and fv = 0 it gives the EMI. Returns a negative number because instalments are outflows - so it is written as -PMT(...). | D7: Goals, Retirement, Calculators
A8: NPER | B8: NPER(rate, pmt, pv, [fv], [type]) | C8: Number of Periods. Solves for TIME. How many months until a SIP reaches a target, or how many months a corpus survives a given withdrawal. | D8: Calculators 6 and 8
A9: RATE | B9: RATE(nper, pmt, pv, [fv]) | C9: Solves for the RETURN needed to get from where you are to where you want to be in the time you have. A reality check: if it demands more than ~14% p.a., the goal itself needs to change. | D9: Calculator 8
A10: INDEX + MATCH | B10: INDEX(return_range, MATCH(value, lookup_range, 1)) | C10: Age-banded table lookup. MATCH with the third argument 1 finds the largest band value that is still less than or equal to the age (so the bands must be sorted ascending); INDEX then returns the matching multiple, premium rate or asset weight. | D10: Insurance, Allocation
A11: MAX / MIN | B11: MAX(a, b, c) / MIN(a, b) | C11: Picks the largest or smallest. Used to plan to the HIGHEST of the three life cover methods, to floor shortfalls at zero, and to cap critical illness cover. | D11: Insurance, Goals, Retirement
A12: CEILING | B12: CEILING(number, significance) | C12: Rounds UP to the next multiple. Insurers sell cover in ₹5L and ₹25L slabs, so requirements are rounded up - never down. | D12: Insurance
A13: IFERROR | B13: IFERROR(value, value_if_error) | C13: Catches divide-by-zero and unsolvable cases so a blank input never turns the sheet into a wall of divide-by-zero errors. | D13: Throughout
A14: SUM | B14: SUM(range) | C14: Adds a range. Used for totals and for netting additions against deductions in the cover calculations. | D14: Throughout
A15: LOG | B15: LOG(number) | C15: Used as LOG(2)/LOG(1+r) to get the exact doubling period - the precise version of the Rule of 72. | D15: Calculator 8
A17: PART 2 - PLANNING FORMULAS BUILT BY HAND
A18: Concept | B18: Formula | C18: Why It Is Built This Way | D18: Used On
A19: Real (inflation-adjusted) return | B19: (1 + Nominal Return) / (1 + Inflation) - 1 | C19: The Fisher equation. Subtracting inflation from return is an approximation that drifts badly over 30+ years. The division is exact and it is what makes long-horizon numbers trustworthy. | D19: Inputs, Retirement, Insurance
A20: Retirement corpus required | B20: PV(real post-ret return, years in retirement, -first-year expense, 0, 1) | C20: Discounting at the REAL rate is the trick: it produces a corpus that supports withdrawals RISING with inflation every year, not a flat pension that halves in purchasing power by age 72. The trailing 1 makes it an annuity-due - money is taken at the start of the year. | D20: Retirement
A21: Expense at retirement | B21: FV(inflation, years to retirement, 0, -today's retirement expense) | C21: Compounds today's cost of living forward. Over 36 years at 6%, this multiplies by roughly 8x - which is the entire reason the corpus number looks so large. | D21: Retirement
A22: Step-up SIP future value | B22: A x [ (1+r)^n - (1+g)^n ] / (r - g) | C22: Future value of a GROWING annuity, where A is the year-1 annual investment, g the annual step-up and r the return. Solved backwards it gives the year-1 SIP needed for a target. When r = g the denominator is zero, so the sheet substitutes A x n x (1+r)^(n-1). | D22: Retirement, Calculator 2
A23: Total invested under a step-up | B23: A x [ (1+g)^n - 1 ] / g | C23: Sum of a geometric series - the contributions alone, ignoring returns. Subtracting it from the corpus isolates how much of the wealth compounding created rather than the client. | D23: Retirement, Calculator 2
A24: Human Life Value | B24: PV(safe real rate, working years, -income net of self-consumption) + liabilities - assets | C24: Discounted at a DEBT-based real rate, not an equity rate. A grieving family should not have to take market risk to make the payout last; assuming 12% would systematically under-insure them. | D24: Insurance
A25: Needs-based cover | B25: PV(family expenses over the dependency period) + liabilities + goal corpuses - existing assets | C25: The most accurate of the three methods because it prices what the family actually needs rather than a multiple of salary. The dependency period runs to the SPOUSE'S life expectancy, not to the earner's retirement date. | D25: Insurance
A26: Health cover requirement | B26: MAX(age benchmark, 50% of income) x city factor x family loading | C26: Cover has to track both the age-driven likelihood of claiming and the income-driven standard of care, then be scaled for local hospital costs and the number of people on the floater. | D26: Insurance
A27: Super top-up structure | B27: Base cover + top-up with a deductible equal to the base | C27: The top-up only pays above the deductible, so it is priced at roughly a quarter to a third of base rates. It is the cheapest way to get large-claim protection, and the reason ₹5L base + ₹20L top-up beats a ₹25L base policy on cost. | D27: Insurance
A28: Goal shortfall | B28: MAX(0, future cost - future value of money already earmarked) | C28: Floored at zero so that an over-funded goal cannot silently subsidise an under-funded one in the totals. | D28: Goals
A29: Purchasing power of a future corpus | B29: corpus / (1 + inflation) ^ years | C29: Deflates a headline crore figure back into today's rupees. Clients understand 'that is ₹1.2 crore in today's money' far better than '₹9.8 crore in 2062'. | D29: Retirement, Projection
A30: Safe withdrawal rate | B30: first-year withdrawal / corpus at retirement | C30: A cross-check on the corpus. At or under 4% is historically survivable for 25 years; a 25-year-plus retirement wants 3-3.5%. If the sheet implies 6%, the corpus is too small no matter what the PV says. | D30: Retirement
A32: COLOUR CONVENTION: blue text on yellow fill = an input you edit | black = a formula on that sheet | green = a value pulled from another sheet | green fill = a headline recommendation

Sheet Tables
A1: LOOKUP TABLES - edit the blue cells to re-benchmark for any client
A3: 1. Life Cover - Income Multiple Thumb Rule | D3: 2. Term Plan - Annual Premium per ₹1 Lakh Cover | G3: 3. Health - Base Cover Benchmark by Age | J3: 4. Health - Annual Premium per ₹1 Lakh Cover
A4: Age From | B4: Multiple of Annual Income | D4: Age From | E4: Premium per ₹1L (₹) | G4: Age From | H4: Base Cover (₹) | J4: Age From | K4: Premium per ₹1L (₹)
A5: 0 | B5: 20 | D5: 0 | E5: 105 | G5: 0 | H5: 500000 | J5: 0 | K5: 1400
A6: 30 | B6: 18 | D6: 30 | E6: 135 | G6: 30 | H6: 750000 | J6: 30 | K6: 1600
A7: 40 | B7: 15 | D7: 35 | E7: 190 | G7: 40 | H7: 1000000 | J7: 40 | K7: 2200
A8: 45 | B8: 12 | D8: 40 | E8: 285 | G8: 50 | H8: 1500000 | J8: 50 | K8: 3600
A9: 50 | B9: 10 | D9: 45 | E9: 450 | G9: 60 | H9: 2500000 | J9: 60 | K9: 6500
A10: 55 | B10: 8 | D10: 50 | E10: 720
D11: 55 | E11: 1150
A14: 5. Asset Allocation Glide Path by Age
A15: Age From | B15: Equity % | C15: Debt % | D15: Gold %
A16: 0 | B16: 0.75 | C16: 0.15 | D16: 0.1
A17: 35 | B17: 0.7 | C17: 0.2 | D17: 0.1
A18: 40 | B18: 0.65 | C18: 0.25 | D18: 0.1
A19: 45 | B19: 0.6 | C19: 0.3 | D19: 0.1
A20: 50 | B20: 0.5 | C20: 0.4 | D20: 0.1
A21: 55 | B21: 0.4 | C21: 0.5 | D21: 0.1
A22: 60 | B22: 0.3 | C22: 0.6 | D22: 0.1
A23: 65 | B23: 0.25 | C23: 0.65 | D23: 0.1
A25: Super top-up premium factor (x base rate per lakh) | B25: 0.3
A26: Critical illness premium per ₹1 lakh (₹ p.a.) | B26: 220
A27: Personal accident premium per ₹1 lakh (₹ p.a.) | B27: 90
A29: Sources / basis: multiples & benchmarks are standard Indian advisory practice (IRDAI-regulated term & indemnity health products). Premium rates are indicative retail quotes for a healthy non-smoker; replace with actual quotes per client.
